{"all":{"data":{"Took action":7506,"Action not necessary":5728,"Found no violation":5366,"Gone":3502,"Summons":3023,"Provided information":1234,"Jurisdiction":1013,"Report":186,"Contact Info":140,"Unable to gain entry to premises":19,"Arrest":8},"total":27725,"percent":11},"122":{"data":{"Took action":87,"Action not necessary":48,"Found no violation":48,"Summons":23,"Gone":15,"Report":5,"Provided information":5,"Jurisdiction":2,"Arrest":2,"Unable to gain entry to premises":2},"total":237,"percent":10},"47":{"data":{"Jurisdiction":146,"Took action":96,"Found no violation":90,"Action not necessary":72,"Summons":42,"Gone":41,"Provided information":8,"Report":1},"total":496,"percent":8},"46":{"data":{"Found no violation":128,"Action not necessary":64,"Provided information":52,"Took action":33,"Summons":24,"Gone":21,"Jurisdiction":7,"Contact Info":4},"total":333,"percent":7},"45":{"data":{"Took action":206,"Gone":140,"Action not necessary":112,"Summons":96,"Found no violation":75,"Jurisdiction":50,"Provided information":41,"Report":5,"Contact Info":4},"total":729,"percent":13},"48":{"data":{"Found no violation":53,"Took action":45,"Gone":30,"Summons":25,"Action not necessary":13,"Provided information":5},"total":171,"percent":15},"109":{"data":{"Took action":317,"Action not necessary":126,"Found no violation":92,"Gone":78,"Summons":51,"Provided information":25,"Report":19,"Jurisdiction":13,"Contact Info":3,"Unable to gain entry to premises":1},"total":725,"percent":7},"20":{"data":{"Took action":57,"Action not necessary":48,"Found no violation":33,"Gone":26,"Summons":17,"Provided information":3,"Jurisdiction":2},"total":186,"percent":9},"94":{"data":{"Action not necessary":272,"Found no violation":167,"Took action":60,"Gone":58,"Summons":32,"Jurisdiction":9,"Provided information":8,"Contact Info":1,"Report":1},"total":608,"percent":5},"44":{"data":{"Found no violation":135,"Took action":71,"Action not necessary":43,"Gone":34,"Summons":24,"Provided information":6,"Jurisdiction":5},"total":318,"percent":8},"62":{"data":{"Action not necessary":227,"Took action":208,"Found no violation":121,"Gone":79,"Summons":53,"Provided information":17,"Jurisdiction":14,"Report":7},"total":726,"percent":7},"77":{"data":{"Action not necessary":113,"Took action":64,"Gone":59,"Found no violation":44,"Summons":26,"Jurisdiction":17,"Report":3,"Provided information":2,"Unable to gain entry to premises":1},"total":329,"percent":8},"52":{"data":{"Took action":275,"Summons":178,"Action not necessary":140,"Found no violation":132,"Gone":89,"Provided information":47,"Jurisdiction":16,"Report":3},"total":880,"percent":20},"120":{"data":{"Took action":126,"Found no violation":62,"Action not necessary":33,"Summons":29,"Gone":19,"Provided information":3,"Jurisdiction":3,"Report":1},"total":276,"percent":11},"71":{"data":{"Took action":111,"Found no violation":63,"Action not necessary":30,"Summons":24,"Gone":12,"Jurisdiction":8,"Provided information":3,"Unable to gain entry to premises":1},"total":252,"percent":10},"23":{"data":{"Took action":26,"Action not necessary":13,"Jurisdiction":12,"Found no violation":8,"Summons":6,"Gone":4,"Provided information":2},"total":71,"percent":8},"1":{"data":{"Took action":131,"Gone":58,"Found no violation":55,"Summons":49,"Action not necessary":26,"Jurisdiction":4,"Provided information":1},"total":324,"percent":15},"68":{"data":{"Took action":213,"Action not necessary":150,"Gone":77,"Found no violation":74,"Summons":49,"Report":6,"Provided information":4,"Unable to gain entry to premises":1,"Contact Info":1},"total":575,"percent":9},"114":{"data":{"Took action":259,"Gone":131,"Action not necessary":123,"Found no violation":116,"Summons":46,"Jurisdiction":22,"Provided information":10,"Arrest":1},"total":708,"percent":6},"111":{"data":{"Took action":110,"Action not necessary":60,"Gone":41,"Found no violation":30,"Summons":19,"Report":5,"Jurisdiction":1,"Provided information":1},"total":267,"percent":7},"60":{"data":{"Took action":47,"Action not necessary":26,"Gone":22,"Found no violation":20,"Summons":7,"Report":2,"Provided information":1,"Jurisdiction":1},"total":126,"percent":6},"67":{"data":{"Took action":75,"Found no violation":65,"Action not necessary":38,"Gone":30,"Summons":28,"Jurisdiction":25,"Provided information":12,"Report":1},"total":274,"percent":10},"63":{"data":{"Took action":244,"Action not necessary":55,"Summons":33,"Gone":29,"Found no violation":19,"Provided information":12,"Jurisdiction":2,"Report":1},"total":395,"percent":8},"107":{"data":{"Took action":74,"Action not necessary":65,"Summons":55,"Gone":47,"Found no violation":44,"Provided information":13,"Report":7,"Jurisdiction":4,"Contact Info":3,"Unable to gain entry to premises":1},"total":313,"percent":18},"90":{"data":{"Action not necessary":128,"Found no violation":67,"Took action":65,"Gone":41,"Summons":31,"Provided information":21,"Jurisdiction":6,"Contact Info":1},"total":360,"percent":9},"33":{"data":{"Found no violation":114,"Action not necessary":102,"Took action":83,"Summons":38,"Provided information":19,"Gone":15,"Contact Info":1},"total":372,"percent":10},"Unknown":{"data":{"Took action":301,"Found no violation":268,"Action not necessary":193,"Gone":147,"Summons":123,"Provided information":65,"Jurisdiction":60,"Report":8,"Contact Info":1},"total":1166,"percent":11},"75":{"data":{"Action not necessary":104,"Provided information":80,"Took action":77,"Found no violation":57,"Jurisdiction":40,"Summons":26,"Gone":21,"Arrest":1,"Report":1},"total":407,"percent":6},"49":{"data":{"Took action":106,"Found no violation":88,"Action not necessary":85,"Summons":75,"Provided information":71,"Gone":71,"Jurisdiction":41,"Unable to gain entry to premises":1,"Report":1},"total":539,"percent":14},"40":{"data":{"Found no violation":94,"Took action":68,"Action not necessary":67,"Summons":30,"Provided information":12,"Gone":7,"Report":2},"total":280,"percent":11},"69":{"data":{"Took action":61,"Action not necessary":22,"Summons":18,"Found no violation":14,"Gone":9,"Jurisdiction":2,"Provided information":1},"total":127,"percent":14},"66":{"data":{"Took action":107,"Summons":92,"Action not necessary":85,"Gone":80,"Found no violation":44,"Provided information":23,"Jurisdiction":15,"Report":3,"Contact Info":1},"total":450,"percent":20},"102":{"data":{"Took action":280,"Action not necessary":208,"Found no violation":155,"Summons":90,"Gone":80,"Provided information":21,"Jurisdiction":20},"total":854,"percent":11},"104":{"data":{"Took action":287,"Gone":248,"Summons":218,"Found no violation":155,"Action not necessary":147,"Provided information":123,"Jurisdiction":5,"Report":3},"total":1186,"percent":18},"121":{"data":{"Took action":115,"Found no violation":45,"Summons":30,"Action not necessary":23,"Gone":14,"Report":8,"Provided information":5},"total":240,"percent":13},"83":{"data":{"Took action":59,"Action not necessary":36,"Found no violation":36,"Summons":19,"Gone":17,"Provided information":13,"Report":8,"Jurisdiction":3,"Contact Info":3,"Unable to gain entry to premises":2,"Arrest":1},"total":197,"percent":10},"28":{"data":{"Took action":42,"Summons":23,"Gone":22,"Action not necessary":21,"Found no violation":19,"Provided information":8,"Jurisdiction":2,"Unable to gain entry to premises":1},"total":138,"percent":17},"50":{"data":{"Found no violation":312,"Gone":263,"Action not necessary":236,"Took action":188,"Summons":101,"Provided information":83,"Jurisdiction":9,"Contact Info":4,"Report":2},"total":1198,"percent":8},"115":{"data":{"Found no violation":218,"Action not necessary":214,"Took action":180,"Gone":91,"Summons":84,"Jurisdiction":68,"Provided information":32,"Report":9,"Unable to gain entry to premises":1},"total":897,"percent":9},"113":{"data":{"Took action":93,"Found no violation":63,"Jurisdiction":55,"Provided information":42,"Action not necessary":25,"Summons":20,"Gone":8},"total":306,"percent":7},"106":{"data":{"Took action":129,"Found no violation":109,"Action not necessary":82,"Jurisdiction":74,"Provided information":72,"Gone":70,"Summons":38,"Report":25},"total":599,"percent":6},"18":{"data":{"Found no violation":53,"Took action":46,"Action not necessary":32,"Gone":26,"Summons":11,"Jurisdiction":2,"Report":1,"Provided information":1},"total":172,"percent":6},"79":{"data":{"Action not necessary":180,"Took action":98,"Found no violation":69,"Jurisdiction":56,"Summons":51,"Contact Info":45,"Gone":27,"Provided information":10,"Arrest":2,"Report":1},"total":539,"percent":9},"110":{"data":{"Took action":134,"Found no violation":124,"Action not necessary":83,"Gone":51,"Summons":35,"Provided information":17,"Unable to gain entry to premises":2,"Jurisdiction":2},"total":448,"percent":8},"81":{"data":{"Took action":61,"Action not necessary":31,"Summons":22,"Found no violation":17,"Gone":7,"Provided information":3,"Jurisdiction":3,"Unable to gain entry to premises":1,"Contact Info":1},"total":146,"percent":15},"70":{"data":{"Action not necessary":85,"Summons":64,"Took action":57,"Gone":52,"Jurisdiction":48,"Found no violation":37,"Report":3,"Provided information":2},"total":348,"percent":18},"108":{"data":{"Took action":146,"Found no violation":139,"Summons":65,"Action not necessary":59,"Gone":47,"Jurisdiction":20,"Provided information":6},"total":482,"percent":13},"30":{"data":{"Found no violation":37,"Action not necessary":35,"Summons":34,"Took action":24,"Gone":12,"Provided information":5,"Jurisdiction":2,"Unable to gain entry to premises":1},"total":150,"percent":23},"34":{"data":{"Took action":216,"Found no violation":197,"Gone":146,"Summons":136,"Action not necessary":135,"Provided information":32,"Jurisdiction":9,"Report":4},"total":875,"percent":16},"105":{"data":{"Took action":132,"Found no violation":67,"Gone":37,"Summons":35,"Action not necessary":25,"Report":13,"Jurisdiction":9,"Provided information":4},"total":322,"percent":11},"17":{"data":{"Action not necessary":26,"Took action":21,"Gone":13,"Summons":9,"Found no violation":5},"total":74,"percent":12},"24":{"data":{"Action not necessary":122,"Found no violation":119,"Took action":56,"Summons":31,"Gone":14,"Jurisdiction":1},"total":343,"percent":9},"43":{"data":{"Found no violation":138,"Action not necessary":104,"Took action":61,"Summons":32,"Gone":32,"Provided information":26,"Contact Info":26,"Jurisdiction":14,"Report":3},"total":436,"percent":7},"6":{"data":{"Took action":22,"Action not necessary":20,"Found no violation":18,"Gone":11,"Summons":3,"Contact Info":2,"Provided information":1},"total":77,"percent":4},"123":{"data":{"Action not necessary":37,"Took action":37,"Summons":22,"Gone":12,"Found no violation":10,"Provided information":3,"Report":2},"total":123,"percent":18},"112":{"data":{"Found no violation":95,"Took action":73,"Gone":67,"Action not necessary":53,"Contact Info":30,"Summons":23,"Provided information":4,"Jurisdiction":3,"Report":1},"total":349,"percent":7},"88":{"data":{"Action not necessary":133,"Took action":64,"Gone":61,"Found no violation":59,"Summons":38,"Provided information":17,"Jurisdiction":10,"Contact Info":8,"Unable to gain entry to premises":1},"total":391,"percent":10},"61":{"data":{"Took action":220,"Action not necessary":165,"Gone":112,"Summons":91,"Found no violation":65,"Report":10,"Provided information":9,"Jurisdiction":9},"total":681,"percent":13},"13":{"data":{"Took action":54,"Action not necessary":33,"Gone":33,"Found no violation":30,"Provided information":26,"Summons":13},"total":189,"percent":7},"78":{"data":{"Action not necessary":124,"Took action":120,"Gone":43,"Found no violation":42,"Summons":19,"Jurisdiction":4,"Arrest":1,"Report":1},"total":354,"percent":5},"84":{"data":{"Gone":121,"Action not necessary":76,"Took action":74,"Found no violation":60,"Summons":40,"Jurisdiction":8,"Provided information":5},"total":384,"percent":10},"19":{"data":{"Took action":57,"Action not necessary":48,"Gone":40,"Found no violation":34,"Summons":26,"Provided information":18,"Jurisdiction":2},"total":225,"percent":12},"41":{"data":{"Took action":44,"Found no violation":26,"Summons":18,"Gone":9,"Action not necessary":8,"Provided information":3,"Jurisdiction":2},"total":110,"percent":16},"42":{"data":{"Took action":40,"Action not necessary":27,"Found no violation":26,"Jurisdiction":8,"Provided information":6,"Gone":6,"Summons":5,"Report":1},"total":119,"percent":4},"7":{"data":{"Action not necessary":20,"Took action":20,"Found no violation":19,"Gone":13,"Summons":12,"Provided information":3},"total":87,"percent":14},"72":{"data":{"Took action":78,"Action not necessary":61,"Found no violation":58,"Gone":34,"Summons":16,"Provided information":3},"total":250,"percent":6},"26":{"data":{"Summons":26,"Action not necessary":21,"Took action":18,"Found no violation":13,"Gone":7,"Jurisdiction":2,"Provided information":1},"total":88,"percent":30},"9":{"data":{"Found no violation":25,"Gone":24,"Took action":23,"Action not necessary":22,"Provided information":9,"Summons":5,"Jurisdiction":1,"Contact Info":1},"total":110,"percent":5},"100":{"data":{"Took action":24,"Found no violation":17,"Summons":11,"Action not necessary":9,"Report":3,"Provided information":1,"Gone":1},"total":66,"percent":17},"5":{"data":{"Took action":41,"Provided information":25,"Action not necessary":14,"Found no violation":12,"Gone":8,"Summons":4},"total":104,"percent":4},"32":{"data":{"Took action":56,"Found no violation":43,"Action not necessary":31,"Summons":23,"Gone":3,"Jurisdiction":1,"Unable to gain entry to premises":1},"total":158,"percent":15},"73":{"data":{"Took action":37,"Found no violation":27,"Action not necessary":15,"Gone":13,"Summons":11,"Jurisdiction":3,"Report":1},"total":107,"percent":10},"103":{"data":{"Action not necessary":89,"Took action":66,"Found no violation":44,"Summons":25,"Gone":20,"Jurisdiction":7,"Provided information":6,"Report":5,"Unable to gain entry to premises":1},"total":263,"percent":10},"101":{"data":{"Found no violation":21,"Took action":18,"Jurisdiction":17,"Provided information":12,"Action not necessary":6,"Gone":5,"Summons":2},"total":81,"percent":2},"76":{"data":{"Action not necessary":55,"Took action":27,"Found no violation":22,"Summons":9,"Gone":7,"Provided information":2},"total":122,"percent":7},"14":{"data":{"Summons":35,"Gone":30,"Found no violation":29,"Took action":27,"Action not necessary":23,"Jurisdiction":2,"Provided information":1},"total":147,"percent":24},"10":{"data":{"Action not necessary":22,"Summons":22,"Found no violation":13,"Took action":9,"Gone":7,"Jurisdiction":1,"Provided information":1},"total":75,"percent":29},"25":{"data":{"Took action":29,"Action not necessary":24,"Found no violation":24,"Summons":7,"Gone":7,"Jurisdiction":4},"total":95,"percent":7}}