{"11434":{"153-06 119 AVENUE":"113C","144-31 166 STREET":"105A","155-09 134 AVENUE":"113B","115-35 MARSDEN STREET":"113C","180 STREET":-1,"137-28 170 STREET":"113B","137-24 170 STREET":"113B","169-15 LINDEN BOULEVARD":"113C","123 AVENUE":-1,"179 STREET":-1,"134-38 161 STREET":"113B","153-20 123 AVENUE":"113C","115-22 BEDELL STREET":"113C","145 AVENUE":-1,"153-08 118 AVENUE":"113C","171-03 143 ROAD":"113B","179-22 143 ROAD":"113B","150 STREET":-1,"167-40 146 AVENUE":"105A","145-90 180 STREET":"105A","122-19 153 STREET":"113C","153-26 123 AVENUE":"113C","132-34 157 STREET":"113B","155-38 115 ROAD":"113C","118-43 153 STREET":"113C","118-16 155 STREET":"113C","118-18 155 STREET":"113C"},"10461":{"2112 WILLIAMSBRIDGE ROAD":"49A","2845 MAITLAND AVENUE":"45B","1835 WILLOW LANE":"45B","1866 HUTCHINSON RIVER PARKWAY":"45B","MULFORD AVENUE":-1,"2800 WILKINSON AVENUE":"45B","2147 TOMLINSON AVENUE":"49A","1314 BRADFORD AVENUE":"45B","2866 HARRINGTON AVENUE":"45B","2500 POPLAR STREET":"49A","1310 BRADFORD AVENUE":"45B","2005 HONE AVENUE":"49A","1516 JARVIS AVENUE":"45B","1510 MAYFLOWER AVENUE":"45B","2110 HONE AVENUE":"49A","3065 ROBERTS AVENUE":"45B","2845 WILKINSON AVENUE":"45B","2121 HONE AVENUE":"49A","1554 HONE AVENUE":"49A","1810 PARKVIEW AVENUE":"45B","MAYFLOWER AVENUE":-1,"1535 MAYFLOWER AVENUE":"45B","1502 HONE AVENUE":"49A","1803 PARKVIEW AVENUE":"45B","1025 ESPLANADE":"49A","1330 HOBART AVENUE":"45B","2961 CODDINGTON AVENUE":"45B","2154 HONE AVENUE":"49A","3002 ROBERTS AVENUE":"45B","ESPLANADE":-1,"1870 HUTCHINSON RIVER PARKWAY":"45B","2429 BUCK STREET":"45B","2422 BUCK STREET":"45B","2611 WESTCHESTER AVENUE":"49A","EAST  194 STREET":-1,"1550 PELHAM PARKWAY SOUTH":"49A","3085 EAST TREMONT AVENUE":"45B","2817 HARRINGTON AVENUE":"45B","1912 PILGRIM AVENUE":"45B","1433 OVERING STREET":"45B","1541 OVERING STREET":"45B","2424 BUCK STREET":"45B","1636 LURTING AVENUE":"49A","2016 COLONIAL AVENUE":"45B","2047 ST PAUL AVENUE":"45B"},"11375":{"91-02 69 AVENUE":"112A","MANSE STREET":-1,"65-40 108 STREET":"112D","65-30 110 STREET":"112D","72-56 MANSE STREET":"112A","110-20 73 ROAD":"112A","70-40 MANSE STREET":"112A","111-55 77 AVENUE":"112A","107-21 71 AVENUE":"112A"},"10466":{"4422 BRUNER AVENUE":"47B","4188 BARNES AVENUE":"47A","4051 PAULDING AVENUE":"47C","3940 BRONX BOULEVARD":"47A","628 EAST  231 STREET":"47A","2129 EDENWALD AVENUE":"47B","1068 EAST  232 STREET":"47C","4611 MONTICELLO AVENUE":"47B","4005 SECOR AVENUE":"47C","4002 SECOR AVENUE":"47C","1718 PITMAN AVENUE":"47B","4056 GRACE AVENUE":"47C","2116 GARRETT PLACE":"47C","4050 GRACE AVENUE":"47C","4419 BRUNER AVENUE":"47B","4600 SETON AVENUE":"47B","EAST  232 STREET":-1,"EAST  237 STREET":-1,"3922 DE REIMER AVENUE":"47C","3911 DE REIMER AVENUE":"47C","4257 BARNES AVENUE":"47B","1225 EAST  233 STREET":"47C","3909 DE REIMER AVENUE":"47C","DEREIMER AVENUE":-1,"4327 CARPENTER AVENUE":"47B","4363 BRONX BOULEVARD":"47B","4311 CARPENTER AVENUE":"47B","4047 GRACE AVENUE":"47C","CRANFORD AVENUE":-1,"3950 SECOR AVENUE":"47C","609 EAST  236 STREET":"47B","4305 CARPENTER AVENUE":"47B","605 EAST  236 STREET":"47B","630 EAST  236 STREET":"47B","603 EAST  236 STREET":"47B","700 EAST  232 STREET":"47A","3919 DYRE AVENUE":"47C","4212 HILL AVENUE":"47B","3815 DYRE AVENUE":"47C","4523 SETON AVENUE":"47B","601 EAST  236 STREET":"47B","1901 NEREID AVENUE":"47B","4054 GRACE AVENUE":"47C","774 EAST  233 STREET":"47A","1900 NEREID AVENUE":"47B","1847 NEREID AVENUE":"47B"},"10452":{"135 MARCY PLACE":"44E","155 EAST  168 STREET":"44E","1344 NELSON AVENUE":"44D","1004 WOODYCREST AVENUE":"44B","920 SUMMIT AVENUE":"44B","1100 RIVER AVENUE":"44C","1165 GERARD AVENUE":"44C","125 MARCY PLACE":"44E","1484 INWOOD AVENUE":"44D","106 MARCY PLACE":"44E","928 GERARD AVENUE":"44C","1530 TOWNSEND AVENUE":"44E","1434 OGDEN AVENUE":"44D","1522 UNIVERSITY AVENUE":"46D","149 EAST  165 STREET":"44C","1056 WALTON AVENUE":"44C","112 EAST CLARKE PLACE":"44E","65 EAST  165 STREET":"44C","1324 OGDEN AVENUE":"44D","1484 JEROME AVENUE":"44E","1058 GERARD AVENUE":"44C","1550 INWOOD AVENUE":"44D","120 MARCY PLACE":"44E","907 SUMMIT AVENUE":"44B","1015 GRAND CONCOURSE":"44C"},"10463":{"275 WEST  230 STREET":"50B","98 VAN CORTLANDT PARK SOUTH":"50A","2657 KINGSBRIDGE TERRACE":"52A","2284 JOHNSON AVENUE":"50C","217 WEST  230 STREET":"50B","210 WEST  230 STREET":"50B","3036 GODWIN TERRACE":"50B","3031 CORLEAR AVENUE":"50B","2630 KINGSBRIDGE TERRACE":"52A","125 WEST  228 STREET":"50B","3975 GOUVERNEUR AVENUE":"50A","5205 BROADWAY":"50B","3188 RIVERDALE AVENUE":"50C","3636 FIELDSTON ROAD":"50C","2716 ARLINGTON AVENUE":"50C","295 WEST  231 STREET":"50B","3980 HILLMAN AVENUE":"50A","3975 HILLMAN AVENUE":"50A","3475 GREYSTONE AVENUE":"50C","3023 CORLEAR AVENUE":"50B","290 WEST  231 STREET":"50B","3900 WALDO AVENUE":"50C","BROADWAY":-1,"FORT CHARLES PLACE":-1,"3001 KINGSBRIDGE AVENUE":"50B","3534 RIVERDALE AVENUE":"50C","250 WEST  230 STREET":"50B","KINGSBRIDGE AVENUE":-1,"3050 CORLEAR AVENUE":"50B","2659 KINGSBRIDGE TERRACE":"52A","CORLEAR AVENUE":-1,"474 WEST  238 STREET":"50C","2651 KINGSBRIDGE TERRACE":"52A","MARBLE HILL AVENUE":-1,"5531 BROADWAY":"50B","2700 KINGS BRIDGE TERRACE":"50A","149 WEST  225 STREET":"50B","GODWIN TERRACE":-1,"2653 KINGSBRIDGE TERRACE":"52A","3016 GODWIN TERRACE":"50B","3970 SAXON AVENUE":"50A","GREYSTONE AVENUE":-1,"237 WEST  230 STREET":"50B","3027 CORLEAR AVENUE":"50B","WALDO AVENUE":-1,"3035 CORLEAR AVENUE":"50B","3830 WALDO AVENUE":"50C","239 WEST  230 STREET":"50B","3880 WALDO AVENUE":"50C","5400 BROADWAY":"50B","3816 WALDO AVENUE":"50C","3899 WALDO AVENUE":"50C","42 FORT CHARLES PLACE":"50B","3970 GOUVERNEUR AVENUE":"50A","3500 RIVERDALE AVENUE":"50C","3015 CORLEAR AVENUE":"50B","3240 RIVERDALE AVENUE":"50C","298 WEST  231 STREET":"50B","5227 BROADWAY":"50B","5204 BROADWAY":"50B","3850 HUDSON MANOR TERRACE":"50C","3120 CORLEAR AVENUE":"50B","3174 RIVERDALE AVENUE":"50C","280 WEST  231 STREET":"50B","3820 WALDO AVENUE":"50C","2700 KINGSBRIDGE TERRACE":"50A","2667 KINGSBRIDGE TERRACE":"52A","241 WEST  230 STREET":"50B","20 FORT CHARLES PLACE":"50B","151 WEST  228 STREET":"50B","1 FORT CHARLES PLACE":"50B","3824 WALDO AVENUE":"50C","3000 KINGSBRIDGE AVENUE":"50B","3503 JOHNSON AVENUE":"50C","161 WEST  231 STREET":"50B","2858 HEATH AVENUE":"50A","34 FORT CHARLES PLACE":"50B","3190 RIVERDALE AVENUE":"50C","3299 CAMBRIDGE AVENUE":"50C","3014 GODWIN TERRACE":"50B","58 MARBLE HILL AVENUE":"50B","184 WEST  237 STREET":"50B","321 WEST  230 STREET":"50B","3856 WALDO AVENUE":"50C","5959 BROADWAY":"50C","231 WEST  230 STREET":"50B","2660 KINGSBRIDGE TERRACE":"52A","3311 GILES PLACE":"50A","3526 JOHNSON AVENUE":"50C","3600 FIELDSTON ROAD":"50C","ALBANY CRESCENT":-1,"220 WEST  234 STREET":"50B","3504 ORLOFF AVENUE":"50A","3593 JOHNSON AVENUE":"50C","454 WEST  238 STREET":"50C","2663 KINGSBRIDGE TERRACE":"52A","217 WEST  233 STREET":"50B","3210 RIVERDALE AVENUE":"50C","3489 FORT INDEPENDENCE STREET":"50A"},"11223":{"2308 WEST   12 STREET":"60B","2925 86 STREET":"61B","280 AVENUE W":"61B","801 GRAVESEND NECK ROAD":"61B","421 VAN SICKLEN STREET":"61B","2164 WEST    6 STREET":"61B","108 STRYKER STREET":"61B","2165 WEST    6 STREET":"61B","112 STRYKER STREET":"61B","273 AVENUE X":"61B","2180 EAST    8 STREET":"61B","2481 WEST    1 STREET":"61B","716 AVENUE V":"61B","496 VAN SICKLEN STREET":"61B","117 STRYKER STREET":"61B","421 APPLEGATE COURT":"62D","LAKE STREET":-1,"128 STRYKER STREET":"61B","182 AVENUE T":"62D"},"10003":{"22 IRVING PLACE":"13A","35 IRVING PLACE":"13A","307 EAST    9 STREET":"9D","43 2 AVENUE":"9C","21 EAST    1 STREET":"9C","122 2 AVENUE":"9D","GREENE STREET":-1,"42 EAST   12 STREET":"6B","51 ST MARKS PLACE":"9D","56 ST MARKS PLACE":"9D","12 ST MARKS PLACE":"9D","63 ST MARKS PLACE":"9D"},"11201":{"218 MYRTLE AVENUE":"88D","122 ASHLAND PLACE":"88D","201 WILLOUGHBY STREET":"88D","445 ALBEE SQUARE":"84C","25 BOND STREET":"84C","ASHLAND PLACE":-1,"319 PACIFIC STREET":"84D","165 YORK STREET":"84B","187 STATE STREET":"84A","150 COURT STREET":"76A","75 SMITH STREET":"84C","193 STATE STREET":"84A","199 STATE STREET":"84A","221 ATLANTIC AVENUE":"84A","145 ADAMS STREET":"84B","40 SIDNEY PLACE":"84A","191 STATE STREET":"84A","11 METROTECH CENTER":"84C","93 HENRY STREET":"84A","58 BERGEN STREET":"84D","205 LIVINGSTON STREET":"84C","291 FLATBUSH AVENUE EXTENSION":"88D","111 HICKS STREET":"84A","DUFFIELD STREET":-1,"316 FLATBUSH AVENUE EXTENSION":"84C","27 BOND STREET":"84C","203 STATE STREET":"84A","310 FLATBUSH AVENUE EXTENSION":"84C","312 FLATBUSH AVENUE EXTENSION":"84C","204 STATE STREET":"84A","201 STATE STREET":"84A","159 SMITH STREET":"84D","122 PACIFIC STREET":"76A","17 BOND STREET":"84C","281 HENRY STREET":"84A","200 JAY STREET":"84B","60 TILLARY STREET":"84A","84 TILLARY STREET":"84A","60 BOERUM PLACE":"84A","19 BOND STREET":"84C","191 WILLOUGHBY STREET":"88D","30 BOND STREET":"84C","28 BOND STREET":"84C","339 ADAMS STREET":"84A","160 SCHERMERHORN STREET":"84C","113 FLEET PLACE":"88D","220 SMITH STREET":"76B"},"10471":{"222 WEST  242 STREET":"50C","6134 SPENCER AVENUE":"50C","5535 NETHERLAND AVENUE":"50C","221 WEST  242 STREET":"50C","216 WEST  242 STREET":"50C","4578 MANHATTAN COLLEGE PARKWAY":"50C","5425 VALLES AVENUE":"50C","275 WEST  261 STREET":"50C","4587 MANHATTAN COLLEGE PARKWAY":"50C","5424 VALLES AVENUE":"50C","4601 ARLINGTON AVENUE":"50C","5455 FIELDSTON ROAD":"50C","4582 MANHATTAN COLLEGE PARKWAY":"50C","5959 INDEPENDENCE AVENUE":"50C","226 WEST  242 STREET":"50C","253 WEST  254 STREET":"50C","6200 SPENCER AVENUE":"50C","6147 LIEBIG AVENUE":"50C","5400 FIELDSTON ROAD":"50C"},"11691":{"265 SEAGIRT AVENUE":"101A","443 BEACH   37 STREET":"101C","219 BEACH   28 STREET":"101C","11-33 NEILSON STREET":"101B","314 BEACH   32 STREET":"101C","42-16 ROCKAWAY BEACH BOULEVARD":"101C","318 BEACH   32 STREET":"101C","409 BEACH   51 STREET":"101D"},"10467":{"3085 DECATUR AVENUE":"52D","853 EAST  219 STREET":"47A","757 SOUTH OAK DRIVE":"47A","2565 BOSTON ROAD":"49C","2707 BARNES AVENUE":"49C","2500 BARKER AVENUE":"49C","3181 WEBSTER AVENUE":"52D","45 EAST MOSHOLU PARKWAY NORTH":"52D","3215 BAINBRIDGE AVENUE":"52D","2561 BOSTON ROAD":"49C","2723 BARNES AVENUE":"49C","3044 HULL AVENUE":"52D","3063 HULL AVENUE":"52D","340 EAST  204 STREET":"52D","3040 HULL AVENUE":"52D","3435 GATES PLACE":"52C","3060 HULL AVENUE":"52D","ASTOR AVENUE":-1,"2251 HOLLAND AVENUE":"49B","2855 BRONX PARK EAST":"49C","2260 BARKER AVENUE":"49B","2385 BARKER AVENUE":"49B","2760 BRONX PARK EAST":"49C","3055 HULL AVENUE":"52D","414 EAST  204 STREET":"52D","2300 BRONX PARK EAST":"49B","3159 HULL AVENUE":"52D","2278 BRONX PARK EAST":"49B","315 EAST  206 STREET":"52D","2561 CRUGER AVENUE":"49C","3050 DECATUR AVENUE":"52D","3320 RESERVOIR OVAL EAST":"52D","3061 HULL AVENUE":"52D","3215 HULL AVENUE":"52D","3227 HULL AVENUE":"52D","3400 RESERVOIR OVAL EAST":"52D","3242 DECATUR AVENUE":"52D","860 EAST  217 STREET":"47A","2280 OLINVILLE AVENUE":"49B","155 EAST MOSHOLU PARKWAY NORTH":"52D","3260 CRUGER AVENUE":"47A","3323 BAINBRIDGE AVENUE":"52D","3228 HULL AVENUE":"52D","332 EAST  205 STREET":"52D"},"11204":{"1715 67 STREET":"62A","6308 24 AVENUE":"62B","1543 WEST    7 STREET":"62B","1931 74 STREET":"62A","261 AVENUE P":"62B","7322 BAY PARKWAY":"62B","5415 19 AVENUE":"66A","1963 73 STREET":"62A","7418 19 AVENUE":"62A","1755 70 STREET":"62A","1722 67 STREET":"62A","74 STREET":"88D","4318 17 AVENUE":"66B","1321 DAHILL ROAD":"66A","1341 DAHILL ROAD":"66A","4312 17 AVENUE":"66B","1702 61 STREET":"62A","2066 73 STREET":"62B","2117 73 STREET":"62B","296 AVENUE P":"62B","6804 19 AVENUE":"62A","4302 16 AVENUE":"66B","1588 WEST    4 STREET":"62B","7324 18 AVENUE":"62A"},"10460":{"784 EAST TREMONT AVENUE":"48C","1515 CHARLOTTE STREET":"42B","1620 ADAMS STREET":"49A","538 VAN NEST AVENUE":"49A","1127 EAST  179 STREET":"48D","1013 BRONX PARK SOUTH":"48D","855 EAST  172 STREET":"42B","1453 LELAND AVENUE":"43E","1580 THIERIOT AVENUE":"43E","1922 CROTONA PARKWAY":"48D","1440 CHARLOTTE STREET":"42B","1844 GUERLAIN STREET":"43E","1461 BEACH AVENUE":"43E","1401 BEACH AVENUE":"43E","1000 EAST TREMONT AVENUE":"48D","1290 RODMAN PLACE":"48D","1742 ADAMS STREET":"49A"},"11378":{"59-31 60 LANE":"104C","66-45 JAY AVENUE":"104C","60-65 59 DRIVE":"104C","59-29 60 LANE":"104C","48-15 54 AVENUE":"108D","53-92 68 STREET":"104C","59-34 60 LANE":"104C","FRESH POND ROAD":-1,"58-29 FRESH POND ROAD":"104D","59-33 60 LANE":"104C","58 ROAD":-1,"53 AVENUE":-1,"60-70 56 AVENUE":"104C","59-53 71 STREET":"104D","71-43 58 AVENUE":"104D","60-67 59 ROAD":"104C","57-77 RUST STREET":"104C","70-03 CALDWELL AVENUE":"104D","56 AVENUE":-1,"59-30 60 LANE":"104C","54-29 63 PLACE":"104C","64-43 53 DRIVE":"104C","60-72 60 STREET":"104C","60-50 60 STREET":"104C","69-23 53 DRIVE":"104C","60-30 53 STREET":"104C","57-18 61 STREET":"104C","60-06 60 STREET":"104C","48-23 54 AVENUE":"108D","57-59 MASPETH AVENUE":"104C","59-04 58 ROAD":"104C","60-16 56 DRIVE":"104C","61-44 56 ROAD":"104C","59-22 60 LANE":"104C","71-19 58 ROAD":"104D","60-37 ELIOT AVENUE":"104C"},"10033":{"611 WEST  180 STREET":"34A","562 WEST  174 STREET":"33C","49 PINEHURST AVENUE":"34B","804 WEST  180 STREET":"34B","403 AUDUBON AVENUE":"34A","655 WEST  177 STREET":"33C","175 PINEHURST AVENUE":"34B","600 WEST  176 STREET":"33C","11 WADSWORTH AVENUE":"33C","344 FT WASHINGTON AVENUE":"33D","3 SOUTH PINEHURST AVENUE":"33D","4270 BROADWAY":"34A","551 WEST  181 STREET":"34A","820 WEST  180 STREET":"34B","551 WEST  184 STREET":"34A","173 PINEHURST AVENUE":"34B","650 WEST  180 STREET":"34A","570 FORT WASHINGTON AVENUE":"34B","454 FORT WASHINGTON AVENUE":"34B","156 PINEHURST AVENUE":"34B","452 FORT WASHINGTON AVENUE":"34B","607 WEST  180 STREET":"34A","125 WADSWORTH AVENUE":"34A","36 LAUREL HILL TERRACE":"34A"},"11103":{"24-37 49 STREET":"114A","25-77 46 STREET":"114A","25-88 49 STREET":"114A","44-20 30 ROAD":"114A","25-42 49 STREET":"114A","30-75 48 STREET":"114A","44-18 30 ROAD":"114A","31-44 47 STREET":"114A","31-46 47 STREET":"114A","25-40 49 STREET":"114A","25-73 43 STREET":"114A","25-96 43 STREET":"114A"},"11377":{"70-01 CALAMUS AVENUE":"108D","28-01 56 PLACE":"114A","32-32 54 STREET":"114A","50-69 46 STREET":"108D","40-33 62 STREET":"108C","51-05 70 STREET":"108D","31-27 56 STREET":"114A","28 AVENUE":-1,"32-22 68 STREET":"115B","48-11 60 STREET":"108D","51-31 70 STREET":"104C","48-24 58 LANE":"108D","64-16 48 AVENUE":"108D","48 AVENUE":-1,"37-78 64 STREET":"108C","70-09 CALAMUS AVENUE":"108D","70-15 CALAMUS AVENUE":"108D","51-35 71 STREET":"108D","56-19 30 AVENUE":"114A","49-13 31 AVENUE":"114A","49-01 31 AVENUE":"114A","51-19 69 PLACE":"104C","70-24 47 AVENUE":"108D","51-04 63 STREET":"108D","70-21 CALAMUS AVENUE":"108D","51-07 70 STREET":"108D","54 STREET":-1,"53-15 QUEENS BOULEVARD":"108C","51-03 43 AVENUE":"108C","37-33 69 STREET":"108C","66-25 GARFIELD AVENUE":"108D","39-37 50 STREET":"108C","51-06 63 STREET":"108D","39-30 52 STREET":"108C","72-41 51 DRIVE":"108D","69-45 CALAMUS AVENUE":"108D","43-13 55 STREET":"108C","70-05 CALAMUS AVENUE":"108D"},"10314":{"12 MARISA COURT":"121D","73 FURNESS PLACE":"121C","193 GANSEVOORT BOULEVARD":"121C","166 WATCHOGUE ROAD":"121B","397 GANSEVOORT BOULEVARD":"121C","KIRSHON AVENUE":-1,"985 RICHMOND AVENUE":"121A","23 EAGLE ROAD":"121B","78 DONGAN AVENUE":"120C","HAROLD STREET":-1,"321 HAROLD STREET":"121C","175 LAMBERTS LANE":"121C"},"11102":{"25-03 23 STREET":"114C","25-05 23 STREET":"114C","30-74 14 STREET":"114D","14-34 30 DRIVE":"114D","9-16 MAIN AVENUE":"114D","25-63 22 STREET":"114C","23-18 24 AVENUE":"114B","27-32 27 STREET":"114C","26-18 18 STREET":"114D","25-46 31 STREET":"114C"},"11216":{"639 DEKALB AVENUE":"79C","397 GREENE AVENUE":"79B","163 KOSCIUSZKO STREET":"79C","365 GREENE AVENUE":"79B","632 LAFAYETTE AVENUE":"79C","635 LAFAYETTE AVENUE":"79C","167 KOSCIUSZKO STREET":"79C","658 DEKALB AVENUE":"79C","GATES AVENUE":-1,"277 GATES AVENUE":"79B","664 DEKALB AVENUE":"79C","261 CLIFTON PLACE":"79C","75 MCDONOUGH STREET":"79A","1151 PACIFIC STREET":"77B","279 CLIFTON PLACE":"79C","357 GREENE AVENUE":"79B","585 LAFAYETTE AVENUE":"79C","1147 PACIFIC STREET":"77B","363 GREENE AVENUE":"79B","485 GREENE AVENUE":"79C","280 HERKIMER STREET":"79A","KOSCIUSZKO STREET":-1,"227 TOMPKINS AVENUE":"79C","669 MARCY AVENUE":"79C","360 GREENE AVENUE":"79B","302 TOMPKINS AVENUE":"79B","34 MAC DONOUGH STREET":"79A","1151 DEAN STREET":"77B","89 KOSCIUSZKO STREET":"79C","651 DEKALB AVENUE":"79C"},"11420":{"130-48 129 STREET":"106D","114-02 LINDEN BOULEVARD":"106B","126-12 OLD SOUTH ROAD":"106A","135-21 125 STREET":"106D","133-28 126 STREET":"106D","111-14 117 STREET":"106B","109-13 118 STREET":"106C","109-31 120 STREET":"106C","129-50 134 STREET":"106D","109-44 132 STREET":"106C","116-04 126 STREET":"106D","117-15 115 AVENUE":"106B","115-26 132 STREET":"106D","109-28 115 STREET":"106C","134-15 115 AVENUE":"106D","126-24 OLD SOUTH ROAD":"106A","109-33 120 STREET":"106C","150-24 129 STREET":"106A","130-32 126 STREET":"106D","111-43 128 STREET":"106D","111-11 117 STREET":"106B","111-11 111 STREET":"106B","135-46 129 STREET":"106D"},"11105":{"45-01 19 AVENUE":"114B","23-44 21 STREET":"114B","23-51 19 STREET":"114B","21-47 31 STREET":"114B","21-51 31 STREET":"114B","23-33 23 STREET":"114B","47-09 21 AVENUE":"114B","19-13 23 DRIVE":"114B","19-17 23 DRIVE":"114B","35-19 DITMARS BOULEVARD":"114B","23-02 STEINWAY STREET":"114B","23-37 36 STREET":"114B","37-11 21 AVENUE":"114B","21-38 31 STREET":"114B","23-90 33 STREET":"114B","24-02 21 AVENUE":"114B","23-88 31 STREET":"114B"},"11435":{"145-54 107 AVENUE":"103C","104-39 142 STREET":"103C","87-43 139 STREET":"107C","139-11 87 DRIVE":"107C","139-15 87 DRIVE":"107C","109 DRIVE":-1,"144-01 HILLSIDE AVENUE":"107C","107-42 REMINGTON STREET":"103C","104-23 142 STREET":"103C","145-32 105 AVENUE":"103C","145-23 106 AVENUE":"103C","145-38 105 AVENUE":"103C","143-12 LIBERTY AVENUE":"103C","147-45 109 AVENUE":"103C","83-40 DANIELS STREET":"107C","147-06 HOOVER AVENUE":"107C","144-12 GRAND CENTRAL PARKWAY SR SOUTH":"107C","145-53 BRINKERHOFF AVENUE":"103C","83-39 DANIELS STREET":"107C","143-10 HOOVER AVENUE":"107C","107-50 REMINGTON STREET":"103C","138-50 102 AVENUE":"103C","84-50 MAIN STREET":"107C","81-06 138 STREET":"107C","135-26 UNION TURNPIKE":"107C","147-16 SOUTH ROAD":"103C","140-74 BURDEN CRESCENT":"107C","83-53 SMEDLEY STREET":"107C","145-09 LAKEWOOD AVENUE":"103C","145-05 LAKEWOOD AVENUE":"103C","143-20 109 AVENUE":"103C","90-10 143 STREET":"103A"},"11217":{"319 FLATBUSH AVENUE":"78C","330 SCHERMERHORN STREET":"84D","334 SCHERMERHORN STREET":"84D","292 SCHERMERHORN STREET":"84C","305 SCHERMERHORN STREET":"84C","146 DEAN STREET":"84D","70 NEVINS STREET":"84C","319 STATE STREET":"84C","252 SCHERMERHORN STREET":"84C","470 STATE STREET":"84D","50 NEVINS STREET":"84C","488 STATE STREET":"84D","112 BOND STREET":"84D","473 BERGEN STREET":"78C","625 ATLANTIC AVENUE":"78C","340 SCHERMERHORN STREET":"84D","300 SCHERMERHORN STREET":"84C","139 5 AVENUE":"78C","126 5 AVENUE":"78A","151 5 AVENUE":"78C","203 SOUTH PORTLAND AVENUE":"88D","202 5 AVENUE":"78A","70 STERLING PLACE":"78C","57 4 AVENUE":"78A","422 PACIFIC STREET":"84D","25 ST MARKS AVENUE":"78C","87 4 AVENUE":"78A","670 BALTIC STREET":"78A","166 5 AVENUE":"78A","77 4 AVENUE":"78A","504 STATE STREET":"84D","71 PARK PLACE":"78C","300 ASHLAND PLACE":"88D","16 STERLING PLACE":"78C","437 STATE STREET":"84D","668 BALTIC STREET":"78A","107 ST JOHNS PLACE":"78C","43 8 AVENUE":"78D","143 4 AVENUE":"78A","311 STATE STREET":"84C","578 BALTIC STREET":"78A","29 ST FELIX STREET":"88D","388 STATE STREET":"84C","494 STATE STREET":"84D","30 NEVINS STREET":"84C","440 ATLANTIC AVENUE":"84D","60 BOND STREET":"84C","85 4 AVENUE":"78A","18 NEVINS STREET":"84C","324 BUTLER STREET":"78A","176 5 AVENUE":"78A","242 HOYT STREET":"76B","85 5 AVENUE":"78C","89 4 AVENUE":"78A","482 STATE STREET":"84D","370 STATE STREET":"84C","398 PACIFIC STREET":"84D"},"11423":{"196-04 89 ROAD":"103B","196-18 89 ROAD":"103B","88-81 195 STREET":"103B","88-21 189 STREET":"103B","90-06 193 STREET":"103B","192-02 HOLLIS AVENUE":"103D","195 STREET":-1,"90-18 181 STREET":"103B","198-08 MC LAUGHLIN AVENUE":"107B","181-12 89 AVENUE":"103B","198-09 100 AVENUE":"103D","203-07 100 AVENUE":"103D","187-11 JAMAICA AVENUE":"103B","86-53 DUNTON STREET":"107B","188-40 WOODHULL AVENUE":"103B","90-16 181 STREET":"103B","98-11 197 STREET":"103B","186-23 HENDERSON AVENUE":"103D"},"11418":{"100-05 88 AVENUE":"102A","86-49 102 STREET":"102A","91-54 117 STREET":"102A","100-25 90 AVENUE":"102A","89-04 113 STREET":"102A","89-14 113 STREET":"102A","86-17 115 STREET":"102D","110-50 84 AVENUE":"102C","86-15 115 STREET":"102D","112-10 93 AVENUE":"102A","86-75 107 STREET":"102D","100-06 88 AVENUE":"102A","102-19 93 AVENUE":"102A","86-73 107 STREET":"102D","86-62 107 STREET":"102D","102-33 86 ROAD":"102D","100-15 88 AVENUE":"102A","84-40 101 STREET":"102D","113-16 93 AVENUE":"102A","87-60 112 STREET":"102A","86-05 115 STREET":"102D","113-20 93 AVENUE":"102A","100-15 93 AVENUE":"102A","86-80 102 STREET":"102A","85-15 115 STREET":"102C","86-56 106 STREET":"102D","84-10 112 STREET":"102C","86-20 114 STREET":"102D","87-31 116 STREET":"102A","87-59 112 STREET":"102A","111-09 85 AVENUE":"102C","89-15 102 STREET":"102A","87-33 116 STREET":"102A","93-06 102 STREET":"102A","84-10 101 STREET":"102D","124-21 HILLSIDE AVENUE":"102C","85-05 108 STREET":"102D","105-15 JAMAICA AVENUE":"102D","102-97 92 AVENUE":"102A","84-22 115 STREET":"102C","114-20 91 AVENUE":"102A","104-09 92 AVENUE":"102A","113-11 BABBAGE STREET":"102C","102-26 92 AVENUE":"102A","88-12 104 STREET":"102A","91-52 LEFFERTS BOULEVARD":"102A"},"11354":{"141-16 25 ROAD":"109C","25-46 123 STREET":"109C","25-07 125 STREET":"109C","33-54 FARRINGTON STREET":"109C","25-17 123 STREET":"109C","28 AVENUE":-1,"25-07 143 STREET":"109C","25-69 125 STREET":"109C","144-51 25 ROAD":"109C","140-42 31 DRIVE":"109C","40-09 PRINCE STREET":"109B","140-46 31 DRIVE":"109C"},"11416":{"86-03 ROCKAWAY BOULEVARD":"102B","101-07 98 STREET":"102B","75-01 97 AVENUE":"102B","95-20 94 STREET":"102B","107-10 95 AVENUE":"102A","76-12 97 AVENUE":"102B","101-27 98 STREET":"102B","85-15 101 AVENUE":"102B","104-20 95 AVENUE":"102A","101-59 97 STREET":"102B","108-01 101 AVENUE":"102A"},"11222":{"728 LEONARD STREET":"94C","285 KINGSLAND AVENUE":"94B","153 MCGUINNESS BOULEVARD":"94C","COMMERCIAL STREET":-1,"172 NORMAN AVENUE":"94C","286 MCGUINNESS BOULEVARD":"94C","175 NORMAN AVENUE":"94C","21 DIVISION PLACE":"94B","738 MANHATTAN AVENUE":"94C","100 NORTH   15 STREET":"94A","1205 MANHATTAN AVENUE":"94C","273 DRIGGS AVENUE":"94C"},"10021":{"413 EAST   69 STREET":"19B","114 EAST   72 STREET":"19B","348 EAST   76 STREET":"19B","231 EAST   76 STREET":"19B","175 EAST   75 STREET":"19B","173 EAST   75 STREET":"19B","1322 2 AVENUE":"19B"},"11214":{"8712 BAY PARKWAY":"62C","8021 17 AVENUE":"62A","139 BAY   32 STREET":"62D","1959 78 STREET":"62A","2081 78 STREET":"62B","2454 BENSON AVENUE":"62D","16 BAY   31 STREET":"62D","20 BAY   31 STREET":"62D","2064 20 LANE":"62C","8721 BAY PARKWAY":"62D","226 BAY   43 STREET":"60B","60 BAY   43 STREET":"60B","126 BAY   43 STREET":"60B","8683 25 AVENUE":"62D","8800 24 AVENUE":"62D","207 BAY   41 STREET":"62D","8733 26 AVENUE":"60B","128 BAY   43 STREET":"60B","2437 HARWAY AVENUE":"62D","376 BAY   44 STREET":"60B","8741 26 AVENUE":"60B","8601 16 AVENUE":"62C","1907 CROPSEY AVENUE":"62C","1854 83 STREET":"62A","49 BAY   38 STREET":"62D"},"11226":{"376 EAST   18 STREET":"70C","1419 DORCHESTER ROAD":"70C","370 MARLBOROUGH ROAD":"70C","65 MARLBOROUGH ROAD":"70D","36 EAST   32 STREET":"67A","360 CLARKSON AVENUE":"67A","22 EAST   29 STREET":"67A","PARADE GROUNDS":"70D","314 EAST   29 STREET":"67B","1001 ROGERS AVENUE":"67A","986 ROGERS AVENUE":"67A","367 EAST   18 STREET":"70C","158 EAST   31 STREET":"67A","413 MARLBOROUGH ROAD":"70C","2415 SNYDER AVENUE":"67A","410 EAST   25 STREET":"67B","465 EAST   26 STREET":"67B","475 EAST   26 STREET":"67B","2616 AVENUE D":"67B","666 EAST   21 STREET":"70C","100 EAST   18 STREET":"70D","21 FAIRVIEW PLACE":"67A","2245 BEDFORD AVENUE":"67A","45 MARTENSE STREET":"70D","2170 BEDFORD AVENUE":"70D","2171 CLARENDON ROAD":"70C"},"11203":{"580 BROOKLYN AVENUE":"71D","618 MIDWOOD STREET":"71D","EAST   49 STREET":-1,"NEW YORK AVENUE":-1,"664 EAST   51 STREET":"67E","AVENUE D":-1,"507 EAST   40 STREET":"67B","3909 SNYDER AVENUE":"67D","1278 NEW YORK AVENUE":"67B","73 EAST   35 STREET":"67A","848 MIDWOOD STREET":"71D","EAST   56 STREET":-1,"3504 AVENUE D":"67B","77 EAST   35 STREET":"67A","1226 NEW YORK AVENUE":"67B","1249 NEW YORK AVENUE":"67B","1214 NEW YORK AVENUE":"67B","595 EAST   56 STREET":"67E","5812 BEVERLEY ROAD":"67E"},"11225":{"192 STERLING STREET":"71C","17 LINCOLN ROAD":"71C","284 SULLIVAN PLACE":"71A","1095 UNION STREET":"71A","89 RUTLAND ROAD":"71C","300 SULLIVAN PLACE":"71A","269 LINCOLN ROAD":"71C","921 WASHINGTON AVENUE":"71A","1042 UNION STREET":"71A","29 STERLING STREET":"71C","156 MONTGOMERY STREET":"71A","MONTGOMERY STREET":-1,"189 MONTGOMERY STREET":"71A","1141 UNION STREET":"71A","145 MONTGOMERY STREET":"71A","127 MONTGOMERY STREET":"71A","1092 CARROLL STREET":"71A","324 MONTGOMERY STREET":"71A","491 ROGERS AVENUE":"71C"},"11236":{"712 EAST   78 STREET":"69C","9505 SEAVIEW COURT":"69D","9808 FLATLANDS AVENUE":"69B","1174 EAST   81 STREET":"69C","1644 EAST   93 STREET":"69D","749 EAST   96 STREET":"67E","10107 FARRAGUT ROAD":"69A","28 PAERDEGAT   15 STREET":"69D","1608 EAST   91 STREET":"69D","1172 EAST   81 STREET":"69C","1246 EAST   85 STREET":"69D","1404 EAST   98 STREET":"69B","32 PAERDEGAT   15 STREET":"69D","940 EAST   99 STREET":"69B","755 EAST   80 STREET":"69C","41 EAST   89 STREET":"67E","1105 EAST   81 STREET":"69C","1024 EAST  100 STREET":"69B","AVENUE A":-1},"11428":{"92-61 222 STREET":"105D","218-02 94 AVENUE":"105D","90-02 210 STREET":"105D","92-18 216 STREET":"105D"},"10455":{"533 EAST  149 STREET":"40C","650 ST ANNS AVENUE":"40D","729 EAST  147 STREET":"40A","658 UNION AVENUE":"40D","494 JACKSON AVENUE":"40A","EAST  152 STREET":-1,"772 SOUTHERN BOULEVARD":"41C","520 BROOK AVENUE":"40A","468 CONCORD AVENUE":"40A","470 JACKSON AVENUE":"40A","662 EAGLE AVENUE":"40D","441 CONCORD AVENUE":"40A","479 JACKSON AVENUE":"40A","664 EAGLE AVENUE":"40D","660 EAGLE AVENUE":"40D","733 EAST  147 STREET":"40A","690 EAST  147 STREET":"40A","601 EAGLE AVENUE":"40D","607 CONCORD AVENUE":"40D","600 CONCORD AVENUE":"40D","644 EAGLE AVENUE":"40D","666 EAGLE AVENUE":"40D","363 EAST  151 STREET":"40C","567 FOX STREET":"41C","627 EAGLE AVENUE":"40D"},"11233":{"20A HULL STREET":"73A","393 HALSEY STREET":"81C","383 SUMPTER STREET":"73A","223 CHAUNCEY STREET":"81D","158 HULL STREET":"73A","49 HULL STREET":"73A","520 DECATUR STREET":"81D","110 THOMAS S BOYLAND STREET":"73A","220 PATCHEN AVENUE":"81D","30 HULL STREET":"73A","1756 PROSPECT PLACE":"73B","222 PATCHEN AVENUE":"81D","438 HANCOCK STREET":"81C","1971 FULTON STREET":"73A","923 HANCOCK STREET":"81B","6 MARCONI PLACE":"73B","366 STUYVESANT AVENUE":"81C","381 SUMPTER STREET":"73A","147 ROCKAWAY AVENUE":"73A","203 HOWARD AVENUE":"81D","ATLANTIC AVENUE":-1,"989 HERKIMER STREET":"81D","295A SUMPTER STREET":"73A","1965 BERGEN STREET":"73B","903 HERKIMER STREET":"81D","150 HULL STREET":"73A","177A HULL STREET":"73A","152 HULL STREET":"73A","140 HULL STREET":"73A"},"11209":{"88 STREET":"88D","371 73 STREET":"68D","7200 RIDGE BOULEVARD":"68D","232 91 STREET":"68A","8718 RIDGE BOULEVARD":"68A","505 OVINGTON AVENUE":"68D","9101 4 AVENUE":"68A","461 72 STREET":"68D","258 82 STREET":"68C","535 85 STREET":"68C","417 79 STREET":"68C","476 76 STREET":"68C","185 MARINE AVENUE":"68A","173 92 STREET":"68A","7805 COLONIAL ROAD":"68C","9233 4 AVENUE":"68A","137 70 STREET":"68D","8936 COLONIAL ROAD":"68A","331 BAY RIDGE PARKWAY":"68D","7204 COLONIAL ROAD":"68D"},"11207":{"314 ASHFORD STREET":"75B","319 ASHFORD STREET":"75B","2377 PITKIN AVENUE":"75B","712 NEW LOTS AVENUE":"75D","374 ASHFORD STREET":"75B","178 JACKIE ROBINSON PARKWAY":"75A","340 GEORGIA AVENUE":"75B","833 BARBEY STREET":"75D","707 SHEFFIELD AVENUE":"75D","DUMONT AVENUE":-1,"2747 FULTON STREET":"75A","1246 HALSEY STREET":"83A","70 VAN SICLEN AVENUE":"75A","1226 HALSEY STREET":"83A","ARLINGTON AVENUE":-1,"74 ARLINGTON AVENUE":"75A","BUSHWICK AVENUE":-1,"60 CONWAY STREET":"75A","12311 FLATLANDS AVENUE":"75D","188 COVERT STREET":"83A","176 JACKIE ROBINSON PARKWAY":"75A","930 WILLIAMS AVENUE":"69A","12 VAN SICLEN AVENUE":"75A","65 SCHENCK AVENUE":"75A","69 ARLINGTON AVENUE":"75A","346 HIGHLAND BOULEVARD":"75A","VAN SICLEN AVENUE":-1,"541 GEORGIA AVENUE":"75B","89 ABERDEEN STREET":"83A"},"11385":{"1710 GATES AVENUE":"104B","67-10 65 STREET":"104B","62-15 74 AVENUE":"104A","64-55 MADISON STREET":"104B","71-55 69 STREET":"104A","67-12 65 STREET":"104B","88-22 74 AVENUE":"104A","65-04 COOPER AVENUE":"104A","71-66 69 STREET":"104A","COOPER AVENUE":-1,"73 STREET":-1,"67-08 65 STREET":"104B","77-05 62 STREET":"104A","60-21 PUTNAM AVENUE":"104B","2016 PALMETTO STREET":"104B","77-02 79 STREET":"104A","60-48 MYRTLE AVENUE":"104B","67-07 65 STREET":"104B","63-57 FRESH POND ROAD":"104B","60-69 80 AVENUE":"104A","68-07 COOPER AVENUE":"104A","78-21 73 PLACE":"104A","64-51 MADISON STREET":"104B","61-56 LINDEN STREET":"104B","1874 CORNELIA STREET":"104B","2020 PALMETTO STREET":"104B","64-50 MADISON STREET":"104B","72-25 67 STREET":"104A","60-04 80 AVENUE":"104A","61-10 MADISON STREET":"104B","2017 PALMETTO STREET":"104B","64-10 MADISON STREET":"104B","64-56 MADISON STREET":"104B","1020 CYPRESS AVENUE":"104B","64-36 MADISON STREET":"104B","64-09 MADISON STREET":"104B","64-30 MADISON STREET":"104B","64-05 MADISON STREET":"104B","89-04 DORAN AVENUE":"104A","64-53 MADISON STREET":"104B","FAIRVIEW AVENUE":-1,"73-05 COOPER AVENUE":"104A","72 STREET":-1,"67-11 65 STREET":"104B","55-33 MADISON STREET":"110A","77-46 79 STREET":"104A","66-49 60 PLACE":"104B","61-32 WOODBINE STREET":"104B","66-53 60 PLACE":"104B","64-13 MADISON STREET":"104B","79-31 60 LANE":"104A","64-19 68 AVENUE":"104B","64-45 MADISON STREET":"104B","64-52 MADISON STREET":"104B","78-66 79 LANE":"104A","GRAND VIEW AVENUE":-1,"77-43 79 STREET":"104A","2029 MENAHAN STREET":"104B","73 PLACE":"114D","61-31 MENAHAN STREET":"104C","69-20 65 STREET":"104B","77-45 79 STREET":"104A","680 SENECA AVENUE":"104B","72-26 67 STREET":"104A","1930 GROVE STREET":"104B","72-44 COOPER AVENUE":"104A","74-45 64 PLACE":"104A","79-57 COOPER AVENUE":"104D","72-05 72 PLACE":"104A","2032 MENAHAN STREET":"104B","73-06 COOPER AVENUE":"104A","78-19 MYRTLE AVENUE":"104A"},"10304":{"62 WAVERLY PLACE":"120D","227 GORDON STREET":"120D","91 SANDS STREET":"120D","225 PARK HILL AVENUE":"120D","32 CHESTER PLACE":"120B","108 TARGEE STREET":"120D","122 TARGEE STREET":"120D","100 TARGEE STREET":"120D","260 PARK HILL AVENUE":"120D","69 PARKHILL COURT":"120D","94 TROSSACH ROAD":"120C"},"11361":{"207-02 33 AVENUE":"111D","47-04 204 STREET":"111C"},"11356":{"129-04 18 AVENUE":"109C","15-04 130 STREET":"109C","131-11 15 AVENUE":"109C","9 AVENUE":-1,"18-48 124 STREET":"109C","14-09 130 STREET":"109C","7-05 119 STREET":"109C","20-48 119 STREET":"109C","113-18 14 ROAD":"109C","123-11 20 AVENUE":"109C","6-11 129 STREET":"109C","11-11 128 STREET":"109C","113-12 14 ROAD":"109C","113-19 14 ROAD":"109C","7-14 COLLEGE PLACE":"109C","11-25 COLLEGE POINT BOULEVARD":"109C","14-21 130 STREET":"109C","11-15 COLLEGE POINT BOULEVARD":"109C","18-45G 129 STREET":"109C","23-32 129 STREET":"109C","23-16 129 STREET":"109C","20-07 129 STREET":"109C"},"11374":{"94-02 63 DRIVE":"112B","64-71 WETHEROLE STREET":"112B","66 AVENUE":-1,"61-55 98 STREET":"112C","62 DRIVE":-1,"96-05 QUEENS BOULEVARD":"112C","63-25 AUSTIN STREET":"112B","97-07 63 ROAD":"112C","69-53 ALDERTON STREET":"112A","PS  206":"112C","97-07 67 AVENUE":"112A","AUBREY AVENUE":-1,"96-09 67 AVENUE":"112A","61-35 JUNCTION BOULEVARD":"112C","61-25 97 STREET":"112C","89-88 COOPER AVENUE":"104A","98-00 62 DRIVE":"112C","61-15 98 STREET":"112C","95-20 63 ROAD":"112C","62-54 97 PLACE":"112C","66-08 102 STREET":"112D","62-54 97 STREET":"112C"},"10462":{"1975 WHITEPLAINS ROAD":"49A","1731 ZEREGA AVENUE":"45B","1853 BRONXDALE AVENUE":"49A","1948 BOGART AVENUE":"49A","1859 BRONXDALE AVENUE":"49A","1837 FOWLER AVENUE":"49A","1610 MATTHEWS AVENUE":"49A","1520 PARKER STREET":"45B","MORRIS PARK AVENUE":-1,"MATTHEWS AVENUE":-1,"2059 MCGRAW AVENUE":"43E","1855 BRONXDALE AVENUE":"49A","1827 BARNES AVENUE":"49A","2001 WHITE PLAINS ROAD":"49A","1824 BARNES AVENUE":"49A","2128 WHITE PLAINS ROAD":"49B","2348 POWELL AVENUE":"43B","2004 WHITE PLAINS ROAD":"49A","VAN NEST AVENUE":-1,"1821 RADCLIFF AVENUE":"49A","1871 MATTHEWS AVENUE":"49A","1891 MCGRAW AVENUE":"43E","1235 ZEREGA AVENUE":"43B","2366 ELLIS AVENUE":"43B","2318 NEWBOLD AVENUE":"43B","BOGART AVENUE":-1,"1910 WHITE PLAINS ROAD":"49A","2039 CRUGER AVENUE":"49B","2157 WALLACE AVENUE":"49B","2190 BOLTON STREET":"49B","925 NEILL AVENUE":"49A","1829 MATTHEWS AVENUE":"49A","780 PELHAM PARKWAY SOUTH":"49B","2181 WALLACE AVENUE":"49B","CASTLE HILL AVENUE":-1,"1718 PAULDING AVENUE":"49A","2362 ELLIS AVENUE":"43B","2279 ELLIS AVENUE":"43B","2163 POWELL AVENUE":"43E","1709 COLDEN AVENUE":"49A"},"11369":{"32-14 110 STREET":"115A","24-05 HUMPHREYS STREET":"115A","31-45 BUELL STREET":"115A","31-50 BUELL STREET":"115A","31-44 BUELL STREET":"115A","32-23 110 STREET":"115A","23-25 100 STREET":"115A","24-35 100 STREET":"115A","25-48 96 STREET":"115A","24 AVENUE":-1,"87 STREET":-1,"32-17 86 STREET":"115B","31-23 97 STREET":"115A","24-42 88 STREET":"115B","25-47 96 STREET":"115A","31-13 96 STREET":"115A","23-01 89 STREET":"115B","31-42 103 STREET":"115A","26-01 97 STREET":"115A","31-44 97 STREET":"115A","32-53 103 STREET":"115A","31-15 96 STREET":"115A","30-67 86 STREET":"115B","31-12 96 STREET":"115A","31-01 86 STREET":"115B","32-48 86 STREET":"115B","32-25 90 STREET":"115B","32-55 86 STREET":"115B","32-36 86 STREET":"115B"},"11432":{"187-14 WEXFORD TERRACE":"107B","90 ROAD":-1,"159-04 84 DRIVE":"107C","187-08 WEXFORD TERRACE":"107B","152-11 89 AVENUE":"103A","161-01 84 AVENUE":"107C","167-11 GRAND CENTRAL PARKWAY SR NORTH":"107A","159-22 NORMAL ROAD":"107C"},"11368":{"97-07 HORACE HARDING EXPRESSWAY":"110C","106-04 NORTHERN BOULEVARD":"115D","33-26 100 STREET":"115D","99-11 39 AVENUE":"115D","55-41 97 STREET":"110C","57-14 XENIA STREET":"110C","33-25 100 STREET":"115D","33-49 106 STREET":"115D","37-84 102 STREET":"115D","99-09 CHRISTIE AVENUE":"110C","38-01 JUNCTION BOULEVARD":"115D","50-25 96 STREET":"110C","38 AVENUE":-1,"105-15 34 AVENUE":"115D","108-22 34 AVENUE":"115D","54-23 108 STREET":"110D","55-25 98 STREET":"110C","50-13 104 STREET":"110C","39 AVENUE":-1,"97-27 57 AVENUE":"110C","46-18 102 STREET":"110C","108-30 43 AVENUE":"110D","102-27 ALSTYNE AVENUE":"110C","34-34 111 STREET":"115D","57-11 VAN DOREN STREET":"110D","49-17 106 STREET":"110C","99-13 NORTHERN BOULEVARD":"115A","108-37 37 DRIVE":"115D","37-91 102 STREET":"115D","108-60 37 DRIVE":"115D","108-51 37 DRIVE":"115D","108-39 37 AVENUE":"115D","101-19 37 AVENUE":"115D","50-28 102 STREET":"110C","37-37 108 STREET":"115D","36-98 109 STREET":"115D","34-74 113 STREET":"115D","45-23 97 STREET":"110C","54-25 101 STREET":"110C"},"11419":{"101-11 118 STREET":"102A","107-41 120 STREET":"106C","95-49 112 STREET":"102A","104-47 LEFFERTS BOULEVARD":"106C","94-02 116 STREET":"102A","95-17 115 STREET":"102A","134-04 107 AVENUE":"106C","107-24 118 STREET":"106C","95-60 113 STREET":"102A","107-50 118 STREET":"106C","107-33 118 STREET":"106C","107-31 121 STREET":"106C","94-10 130 STREET":"102A","107-12 127 STREET":"106C","94-16 130 STREET":"102A","108-10 101 AVENUE":"102A","107-59 118 STREET":"106C","104-35 125 STREET":"106C","94-41 112 STREET":"102A","95-51 110 STREET":"102A","101-34 130 STREET":"102A","104-28 132 STREET":"106C","97-02 VAN WYCK EXPRESSWAY SR WEST":"102A","102-02 VAN WYCK EXPRESSWAY":"102A","124-20 101 AVENUE":"102A","107-53 123 STREET":"106C"},"11230":{"1360 OCEAN AVENUE":"70B","1562 AVENUE M":"70A","899 EAST    7 STREET":"70B","612 ARGYLE ROAD":"70C","AVENUE P":-1,"887 EAST    7 STREET":"70B","881 EAST    7 STREET":"70B","212 PARKVILLE AVENUE":"70B","1252 EAST   19 STREET":"70A","AVENUE I":-1,"23 WELLINGTON COURT":"70B","402 AVENUE O":"66A","855 EAST   19 STREET":"70B","1620 EAST    2 STREET":"66A","1649 EAST    2 STREET":"66A","1583 EAST    2 STREET":"66A"},"11357":{"141-07 20 AVENUE":"109C","22-18 LEE STREET":"109C","145-24 22 AVENUE":"109C","145-41 23 AVENUE":"109C","149-12 20 ROAD":"109C","149-16 19 AVENUE":"109D","11-02 147 STREET":"109D","157-47 17 ROAD":"109D","145-25 23 AVENUE":"109C","22-22 LEE STREET":"109C","16-64 156 STREET":"109D","150-22 19 AVENUE":"109D","24-43 157 STREET":"109D","149-12 19 AVENUE":"109D","163-25 16 ROAD":"109D","22-23 LEE STREET":"109C","147-37 20 AVENUE":"109D","150-44 15 DRIVE":"109D","15 ROAD":-1,"149-39 6 AVENUE":"109D","15-68 150 PLACE":"109D","6-52 151 STREET":"109D","6-53 151 STREET":"109D","151-47 7 AVENUE":"109D","6-56 151 STREET":"109D","149-11 15 ROAD":"109D","151-49 7 AVENUE":"109D","5-30 150 STREET":"109D","151-10 10 AVENUE":"109D","151-49 POWELLS COVE BOULEVARD":"109D","30-56 WHITESTONE EXPRESSWAY":"109C","15 DRIVE":-1,"149-27 6 AVENUE":"109D","151-47 POWELLS COVE BOULEVARD":"109D","23-04 143 STREET":"109C","147-54 7 AVENUE":"109D","15-43 144 STREET":"109D"},"10302":{"25 PORT RICHMOND AVENUE":"121B","984 POST AVENUE":"121B","60 NICHOLAS AVENUE":"121B","57 NICHOLAS AVENUE":"121B","51 NICHOLAS AVENUE":"121B","24 DIXON AVENUE":"121B"},"10040":{"708 WEST  192 STREET":"34B","570 WEST  190 STREET":"34A","1598 ST NICHOLAS AVENUE":"34A","598 WEST  191 STREET":"34A","20 BOGARDUS PLACE":"34C","1 WADSWORTH TERRACE":"34A","658 WEST  188 STREET":"34A","655 WEST  190 STREET":"34A","599 WEST  190 STREET":"34A","652 WEST  189 STREET":"34A","1 BROADWAY TERRACE":"34A","666 WEST  188 STREET":"34A","7 BROADWAY TERRACE":"34A","515 WEST  188 STREET":"34A","124 FORT GEORGE AVENUE":"34A","273 BENNETT AVENUE":"34B","HILLSIDE AVENUE":-1,"71 ARDEN STREET":"34D","565 WEST  192 STREET":"34A","141 NAGLE AVENUE":"34C","560 WEST  192 STREET":"34A","1601 ST NICHOLAS AVENUE":"34A","1650 ST NICHOLAS AVENUE":"34A","1610 ST NICHOLAS AVENUE":"34A","1630 ST NICHOLAS AVENUE":"34A","492 AUDUBON AVENUE":"34A","81 WADSWORTH TERRACE":"34A","151 NAGLE AVENUE":"34C","317 WADSWORTH AVENUE":"34A","1594 ST NICHOLAS AVENUE":"34A"},"11205":{"600 DEKALB AVENUE":"79C","32 KOSCIUSZKO STREET":"79C","31 KOSCIUSZKO STREET":"79C","99 NORTH PORTLAND AVENUE":"88C","70 KOSCIUSZKO STREET":"79C","566 DEKALB AVENUE":"79C","68 KOSCIUSZKO STREET":"79C","112 ST EDWARD STREET":"88C","728 MYRTLE AVENUE":"79C","14 KOSCIUSZKO STREET":"79C","43 VANDERBILT AVENUE":"88C","475 DEKALB AVENUE":"79D","479 DEKALB AVENUE":"79D","123 WAVERLY AVENUE":"88B","128 FLUSHING AVENUE":"88C","2 LITTLE NASSAU STREET":"79D","170 WASHINGTON PARK":"88C","243 WASHINGTON AVENUE":"88B","448 LAFAYETTE AVENUE":"79B","87 KOSCIUSZKO STREET":"79C","114 WASHINGTON AVENUE":"88B","217 CLINTON AVENUE":"88B","125 TAAFFE PLACE":"79D","429 FLUSHING AVENUE":"90B","488 LAFAYETTE AVENUE":"79B","278 NOSTRAND AVENUE":"79C","28 KOSCIUSZKO STREET":"79C"},"10039":{"84 BRADHURST AVENUE":"32D","100 BRADHURST AVENUE":"32D","68 BRADHURST AVENUE":"32D","90 BRADHURST AVENUE":"32D","28 MACOMBS PLACE":"32D","32 MACOMBS PLACE":"32D","100 WEST  147 STREET":"32D","26 MACOMBS PLACE":"32D"},"10453":{"1683 UNIVERSITY AVENUE":"46E","2160 WALTON AVENUE":"46C","1730 POPHAM AVENUE":"46E","50 CAMERON PLACE":"46C","10 WEST  182 STREET":"46D","1685 UNIVERSITY AVENUE":"46E","1697 NELSON AVENUE":"46D","95 BRANDT PLACE":"46D","1691 NELSON AVENUE":"46D","125 WEST TREMONT AVENUE":"46D","2056 CRESTON AVENUE":"46C","1749 GRAND CONCOURSE":"46A","1804 HARRISON AVENUE":"46D","1687 NELSON AVENUE":"46D","1706 NELSON AVENUE":"46D","2007 UNIVERSITY AVENUE":"46E","1777 GRAND CONCOURSE":"46A","1715 WALTON AVENUE":"46A","62 CLIFFORD PLACE":"46A","1791 TOWNSEND AVENUE":"46A","1723 TOWNSEND AVENUE":"46A","40 EAST  175 STREET":"46A","1720 TOWNSEND AVENUE":"46A","1840 PHELAN PLACE":"46E","2015 GRAND AVENUE":"46D","2165 WALTON AVENUE":"46C","65 WEST  181 STREET":"46D","2150 UNIVERSITY AVENUE":"46D","1995 SEDGWICK AVENUE":"46E","1998 SEDGWICK AVENUE":"46E"},"11235":{"17 EXETER STREET":"61D","2654 EAST   19 STREET":"61D","9 EXETER STREET":"61D","2914 CONEY ISLAND AVENUE":"60B","3036 BRIGHTON    3 STREET":"60A","10 EXETER STREET":"61D","2467 EAST   27 STREET":"61D","2811 HARING STREET":"61D","2680 EAST   12 STREET":"61D","601 BOARDWALK EAST":"60A","2735 EAST   13 STREET":"61D","2790 BRIGHTON    8 STREET":"60B","1418 SHORE BOULEVARD":"61D","2536 EAST   14 STREET":"61D","2556 EAST   14 STREET":"61D","219 BRIGHTWATER COURT":"60A","2112 AVENUE Y":"61D","1 EXETER STREET":"61D"},"11234":{"1576 EAST   52 STREET":"63C","1562 EAST   51 STREET":"63C","3818 FLATLANDS AVENUE":"63B","2501 FLATBUSH AVENUE":"63A","EAST   48 STREET":-1,"915 EAST   54 STREET":"63D","1578 EAST   52 STREET":"63C","5201 AVENUE N":"63C","1562 EAST   52 STREET":"63C","7221 AVENUE N":"63A","4514 AVENUE L":"63C","2002 EAST   61 STREET":"63C","2034 EAST   67 STREET":"63A","2047 EAST   67 STREET":"63A","2042 EAST   63 STREET":"63A","1494 EAST   59 STREET":"63C","2233 RYDER STREET":"63B","4809 AVENUE J":"63C","2184 EAST   36 STREET":"63B","1231 EAST   68 STREET":"63A","5007 AVENUE O":"63C","2182 EAST   36 STREET":"63B","3521 QUENTIN ROAD":"63B","1281 EAST   73 STREET":"63A","7538 AVENUE T":"63A","1151 EAST   59 STREET":"63C","EAST   51 STREET":-1,"2024 RALPH AVENUE":"63C","1425 EAST   49 STREET":"63C","1433 EAST   49 STREET":"63C","2076 PEARSON STREET":"63C","2230 TROY AVENUE":"63C","2520 RALPH AVENUE":"63C","6633 AVENUE M":"63A","1645 EAST   56 STREET":"63C","1015 EAST   52 STREET":"63D","2197 SCHENECTADY AVENUE":"63C","2210 SCHENECTADY AVENUE":"63C","2524 RALPH AVENUE":"63C","1487 EAST   49 STREET":"63C","5805 AVENUE M":"63C","6108 AVENUE T":"63C","1298 EAST   58 STREET":"63C","1642 EAST   33 STREET":"63B","1236 EAST   59 STREET":"63C","1232 EAST   59 STREET":"63C","1378 EAST   49 STREET":"63C","2177 EAST   37 STREET":"63B","1517 KIMBALL STREET":"63B","1389 EAST   35 STREET":"63B","1515 KIMBALL STREET":"63B","3606 FILLMORE AVENUE":"63B","1858 EAST   49 STREET":"63C","2019 EAST   56 STREET":"63C","1412 EAST   49 STREET":"63C","2017 EAST   56 STREET":"63C","1516 KIMBALL STREET":"63B","2025 EAST   57 STREET":"63C","1414 EAST   49 STREET":"63C","5321 GLENWOOD ROAD":"63D","1803 RYDER STREET":"63B","AVENUE N":-1,"1410 EAST   49 STREET":"63C","1582 EAST   52 STREET":"63C"},"11106":{"34-48 30 STREET":"114C","32-35 30 STREET":"114C","34-02 31 STREET":"114C","14-07 31 DRIVE":"114D","34-09 31 STREET":"114C","31-07 14 STREET":"114D","12-36 31 DRIVE":"114D","31 AVENUE":-1,"29-20 34 AVENUE":"114C","34-00 31 STREET":"114C","21-10 BROADWAY":"114C","35-27 10 STREET":"114D","35-39 10 STREET":"114D","31-44 34 STREET":"114C","34-48 9 STREET":"114D"},"10469":{"3144 MICKLE AVENUE":"47D","3237 WICKHAM AVENUE":"47D","2501 COLDEN AVENUE":"49C","912 EAST  214 STREET":"47D","930 EAST  218 STREET":"47D","3136 MICKLE AVENUE":"47D","3530 MICKLE AVENUE":"47D","FENTON AVENUE":-1,"ADEE AVENUE":-1,"2436 SEYMOUR AVENUE":"49B","1012 EAST  220 STREET":"47D","2546 HONE AVENUE":"49B","1450 ALLERTON AVENUE":"49B","2430 SEYMOUR AVENUE":"49B","3354 GUNTHER AVENUE":"47D","2900 WILLIAMSBRIDGE ROAD":"49C","3219 GRACE AVENUE":"47D","2459 FENTON AVENUE":"49B","1005 ADEE AVENUE":"47A","2732 BOUCK AVENUE":"49C","2530 PEARSALL AVENUE":"49B","2801 EDSON AVENUE":"47D","2577 SEYMOUR AVENUE":"49B","3241 WICKHAM AVENUE":"47D","1290 WARING AVENUE":"49B","2533 FENTON AVENUE":"49B","1135 PELHAM PARKWAY NORTH":"49B"},"11379":{"78-27 69 AVENUE":"104D","66-59 78 STREET":"104D","85-21 60 DRIVE":"104D","85-31 60 DRIVE":"104D","57-39 81 STREET":"104D","65-51 79 PLACE":"104D","85-30 60 DRIVE":"104D","65-43 79 PLACE":"104D","58-02 84 STREET":"104D","58-02 81 STREET":"104D","78-04 QUEENS MIDTOWN EXPRESSWAY":"104D","78-06 58 AVENUE":"104D","83-28 60 AVENUE":"104D","66-01 70 STREET":"104D","57-59 79 STREET":"104D","65-34 79 PLACE":"104D","83-27 60 AVENUE":"104D","64-14 83 PLACE":"104D","58-01 83 STREET":"104D","70-09 62 DRIVE":"104D","62-25 79 STREET":"104D","85-11 60 DRIVE":"104D","85-36 60 DRIVE":"104D","85-34 60 DRIVE":"104D","72 STREET":-1,"65-30 ADMIRAL AVENUE":"104D","60-65 76 STREET":"104D","82-28 61 DRIVE":"104D","62-70 82 STREET":"104D","82-53 CALDWELL AVENUE":"104D","82-53 61 DRIVE":"104D","62-57 69 STREET":"104D","62-21 71 STREET":"104D","62-54 71 STREET":"104D","70-06 ELIOT AVENUE":"104D","66 ROAD":-1,"65-25 79 STREET":"104D","66-46 PLEASANT VIEW STREET":"104D","62-63 69 STREET":"104D"},"10034":{"187 VERMILYEA AVENUE":"34D","584 ACADEMY STREET":"34C","28 POST AVENUE":"34C","647 WEST  207 STREET":"34D","72 COOPER STREET":"34D","2 PARK TERRACE EAST":"34D","268 DYCKMAN STREET":"34D","55 PAYSON AVENUE":"34D","100 SEAMAN AVENUE":"34D","230 SEAMAN AVENUE":"34D","530 WEST  215 STREET":"34D","57 VERMILYEA AVENUE":"34D","4035 10 AVENUE":"34D","616 ACADEMY STREET":"34D","3910 10 AVENUE":"34D","500 WEST  211 STREET":"34D","410 WEST  220 STREET":"34D","83 PAYSON AVENUE":"34D","70 POST AVENUE":"34C","1 PARK TERRACE EAST":"34D"},"11231":{"248 CARROLL STREET":"76A","246 CARROLL STREET":"76A","72 2 PLACE":"76A","27 LUQUER STREET":"76C","504 SMITH STREET":"76A","15 WEST    9 STREET":"76D","13 WEST    9 STREET":"76D","70 2 PLACE":"76A","48 BUTLER STREET":"76B"},"11433":{"109-20 164 PLACE":"103D","111 AVENUE":-1,"105 AVENUE":-1,"109-24 MERRICK BOULEVARD":"103D","106-33 156 STREET":"103C","168-44 LIBERTY AVENUE":"103D","157 STREET":-1,"94-10 MERRICK BOULEVARD":"103D","170-11 93 AVENUE":"103A","173-42 105 AVENUE":"103D","109 ROAD":-1,"160-25 CLAUDE AVENUE":"113C","108-40 155 STREET":"103C","170-11 104 AVENUE":"103D","92-61 165 STREET":"103A","180-14 93 AVENUE":"103B","175-09 LIBERTY AVENUE":"103D"},"11421":{"96-03 91 AVENUE":"102B","84-02 94 STREET":"102D","80-12 85 DRIVE":"102D","89-40 84 STREET":"102B","89-40 85 STREET":"102B","93-12 74 PLACE":"102B","85-14 76 STREET":"102D","79 STREET":-1,"91-05 97 STREET":"102B","88-20 85 ROAD":"102D","84-24 90 STREET":"102D","90-07 80 STREET":"102B","83 STREET":-1,"84-28 90 STREET":"102D","91-08 97 STREET":"102B","91-56 86 STREET":"102B","80-27 87 ROAD":"102B","76-49 85 DRIVE":"102D","76-11 85 DRIVE":"102D","74-38 JAMAICA AVENUE":"102B","92-51 75 STREET":"102B","87-19 89 STREET":"102B","85-06 76 STREET":"102D","74-50 PARK LANE SOUTH":"102D","93-12 91 AVENUE":"102B","85-01 91 STREET":"102D","80-09 89 AVENUE":"102B","89-06 91 AVENUE":"102B","91-44 86 STREET":"102B","85-10 76 STREET":"102D","88-01 ATLANTIC AVENUE":"102B","91-48 86 STREET":"102B","80-73 87 AVENUE":"102B","86-51 91 STREET":"102D","91-18 85 STREET":"102B","91-57 86 STREET":"102B","76-23 85 DRIVE":"102D","80-48 87 AVENUE":"102B","96-16 91 AVENUE":"102B","80-44 87 AVENUE":"102B","89 AVENUE":-1,"89-33 96 STREET":"102B","91-52 85 STREET":"102B","80-69 87 AVENUE":"102B","76-25 85 DRIVE":"102D","75 STREET":-1,"76-38 85 DRIVE":"102D","80-12 87 ROAD":"102B","78-29 90 AVENUE":"102B","89-19 86 ROAD":"102D","85 AVENUE":-1,"91-12 86 STREET":"102B","84-32 90 STREET":"102D","93-31 85 ROAD":"102D","87-35 86 STREET":"102B","80-67 89 AVENUE":"102B","92-18 77 STREET":"102B"},"10009":{"303 EAST    4 STREET":"9A","AVENUE D":-1,"1 AVENUE":"9A","501 EAST    6 STREET":"9A","AVENUE A":-1,"401 EAST    8 STREET":"9A","177 AVENUE B":"9B"},"10468":{"2840 SEDGWICK AVENUE":"50A","2757 MORRIS AVENUE":"52B","6 FORDHAM HILL OVAL":"52A","2914 JEROME AVENUE":"52C","2928 JEROME AVENUE":"52C","LORING PLACE NORTH":-1,"2441 JEROME AVENUE":"52A","2822 WEBB AVENUE":"50A","2825 WEBB AVENUE":"50A","2251 HAMPDEN PLACE":"52A","BEDFORD PARK BOULEVARD":-1,"2302 MORRIS AVENUE":"46C","2835 WEBB AVENUE":"50A","2847 WEBB AVENUE":"50A","2850 WEBB AVENUE":"50A","2860 WEBB AVENUE":"50A","2802 CLAFLIN AVENUE":"50A","2885 JEROME AVENUE":"52C","2312 LORING PLACE NORTH":"52A","2855 CLAFLIN AVENUE":"50A","2876 CLAFLIN AVENUE":"50A","2832 WEBB AVENUE":"50A","2849 WEBB AVENUE":"50A","18 EAST KINGSBRIDGE ROAD":"52B","2859 WEBB AVENUE":"50A","2890 SEDGWICK AVENUE":"50A","2523 DAVIDSON AVENUE":"52A","121 WEST  197 STREET":"50A","136 WEST  197 STREET":"50A","2727 JEROME AVENUE":"52C","2820 UNIVERSITY AVENUE":"50A","123 WEST  197 STREET":"50A","2727 RESERVOIR AVENUE":"50A","2604 SEDGWICK AVENUE":"52A","2739 WEBB AVENUE":"50A","10 WEST  195 STREET":"52C","2895 RESERVOIR AVENUE":"50A","75 WEST  190 STREET":"52A","3123 PAUL AVENUE":"52C","2851 WEBB AVENUE":"50A"},"11238":{"303 GREENE AVENUE":"79B","333 GREENE AVENUE":"79B","1045 ATLANTIC AVENUE":"79A","CARLTON AVENUE":-1,"630 BERGEN STREET":"78C","462 CARLTON AVENUE":"88D","422 LAFAYETTE AVENUE":"79B","493 LINCOLN PLACE":"77A","600 FRANKLIN AVENUE":"77A","564 ST JOHNS PLACE":"77A","418 LAFAYETTE AVENUE":"79B","603 FRANKLIN AVENUE":"77B","502 LINCOLN PLACE":"77A","472 CARLTON AVENUE":"88D","399 ST JOHNS PLACE":"77A","529 FRANKLIN AVENUE":"79A","27 MADISON STREET":"79B","310 GREENE AVENUE":"79B","483 PARK PLACE":"77A","621 PARK PLACE":"77A","608 FRANKLIN AVENUE":"77A","569 GRAND AVENUE":"77A","302 ST JAMES PLACE":"88A","613 WASHINGTON AVENUE":"77A","786 FRANKLIN AVENUE":"77A"},"11215":{"426 17 STREET":"72A","356 3 STREET":"78A","199 7 AVENUE":"78D","363 3 STREET":"78A","206 7 AVENUE":"78B","359 5 AVENUE":"78B","555 4 AVENUE":"72A","234 14 STREET":"78A","2 STREET":"88D","318 5 AVENUE":"78A","169 15 STREET":"78A","119 PROSPECT PARK WEST":"78D","415 5 AVENUE":"78B","559 4 AVENUE":"72A","297 22 STREET":"72A","555 7 AVENUE":"72A","401 FOURTH AVENUE":"78A","BARTEL PRITCHARD SQUARE":"72A","337 21 STREET":"72A","281 5 AVENUE":"78B"},"11417":{"133-02 86 STREET":"106B","105-15 LIBERTY AVENUE":"106C","89-25 ALBERT ROAD":"106B","104-25 103 STREET":"106C","CROSS BAY BOULEVARD":-1,"86-00 107 AVENUE":"106B","103-11 103 STREET":"106C","93-08 LIBERTY AVENUE":"106B","93-10 LIBERTY AVENUE":"106B","84-08 107 AVENUE":"106B","103-02 PLATTWOOD AVENUE":"106B","97-21 PITKIN AVENUE":"106B","103-10 103 STREET":"106C","105-51 90 STREET":"106B","104-04 103 STREET":"106C","103-02 LIBERTY AVENUE":"106C","98-01 LIBERTY AVENUE":"106C"},"11413":{"218-47 140 AVENUE":"105B","143-09 222 STREET":"105B","137 AVENUE":-1,"146-09 225 STREET":"105A","146-57 230 STREET":"105A","223-16 147 AVENUE":"105A","137-19 CARSON STREET":"105B","221-04 130 AVENUE":"105B","143-13 184 STREET":"113B","144-24 222 STREET":"105A","135-02 232 STREET":"105B","223-15 134 ROAD":"105B","143-30 230 PLACE":"105A"},"11365":{"198-18 51 AVENUE":"111C","72-04 164 STREET":"107A","48-07 190 STREET":"111C","164-10 METCALF AVENUE":"109A","50-02 199 STREET":"111C","197-10C 65 CRESCENT":"107B","69-28 167 STREET":"107A","69-29 167 STREET":"107A"},"10031":{"600 WEST  142 STREET":"30B","660 RIVERSIDE DRIVE":"30B","521 WEST  146 STREET":"30B","BROADWAY":-1,"701 WEST  135 STREET":"30C","614 WEST  152 STREET":"30C","514 WEST  135 STREET":"30A","618 WEST  141 STREET":"30A","524 WEST  149 STREET":"30C","403 WEST  148 STREET":"30C","622 RIVERSIDE DRIVE":"30A","458 WEST  153 STREET":"30C","52 ST NICHOLAS PLACE":"30C","48 ST NICHOLAS PLACE":"30C","547 WEST  149 STREET":"30C","545 WEST  148 STREET":"30C","538 WEST  148 STREET":"30B","377 EDGECOMBE AVENUE":"30C","610 WEST  141 STREET":"30A","CONVENT AVENUE":-1,"517 WEST  147 STREET":"30B","610 WEST  152 STREET":"30C"},"10454":{"281 BRUCKNER BOULEVARD":"40A","466 EAST  145 STREET":"40B","222 WILLIS AVENUE":"40B","400 EAST  143 STREET":"40B","429 EAST  142 STREET":"40B","357 EAST  144 STREET":"40B","456 EAST  145 STREET":"40B","471 EAST  142 STREET":"40B","341 BROOK AVENUE":"40B","346 POWERS AVENUE":"40A","383 EAST  143 STREET":"40B","344 BROOK AVENUE":"40A","920 EAST  132 STREET":"40A","688 EAST  135 STREET":"40A","178 BRUCKNER BOULEVARD":"40A","423 EAST  142 STREET":"40B"},"11232":{"268 36 STREET":"72B","178 33 STREET":"72B","274 36 STREET":"72B","227 34 STREET":"72B","215 33 STREET":"72B","208 31 STREET":"72B","875 43 STREET":"66C","416 41 STREET":"72C","176 33 STREET":"72B","9 AVENUE":"66D","4122 5 AVENUE":"72C","4215 8 AVENUE":"66C","637 4 AVENUE":"72A","4323 9 AVENUE":"66C","204 32 STREET":"72B","820 39 STREET":"66C","483 38 STREET":"72B","4016 6 AVENUE":"72C"},"10012":{"566 LA GUARDIA PLACE":"6A","215 MULBERRY STREET":"5C","66 MERCER STREET":"1D","118 PRINCE STREET":"1D","54 BOND STREET":"9C","172 PRINCE STREET":"1D","195 SPRING STREET":"1D","101 CROSBY STREET":"5C"},"11422":{"234-18 147 AVENUE":"105A","241-07 148 ROAD":"105A","121-45 237 STREET":"105B","147-09 235 STREET":"105A","139 AVENUE":-1,"149-53 258 STREET":"105A","257-40 148 AVENUE":"105A"},"10465":{"295 THROGS NECK BOULEVARD":"45A","3750 BRUCKNER BOULEVARD":"45B","3410 BRUCKNER BOULEVARD":"45B","279 SWINTON AVENUE":"45A","2819 SCHURZ AVENUE":"45A","948 CLARENCE AVENUE":"45A","3177 BAISLEY AVENUE":"45A","1106 ELLSWORTH AVENUE":"45A","1118 ELLSWORTH AVENUE":"45A","3175 WISSMAN AVENUE":"45A","3168 WISSMAN AVENUE":"45A","3162 PHILIP AVENUE":"45A","3584 EAST TREMONT AVENUE":"45A","3585 EAST TREMONT AVENUE":"45A","3153 LAFAYETTE AVENUE":"45A","758 SWINTON AVENUE":"45A","2800 PHILIP AVENUE":"45A","718 CALHOUN AVENUE":"45A","1057 QUINCY AVENUE":"45A","264 EMERSON AVENUE":"45A","960 THROGS NECK EXPRESSWAY":"45A","760 THROGS NECK EXPRESSWAY":"45A","3265A BARKLEY AVENUE":"45A","3186 HATTING PLACE":"45A","237 BALCOM AVENUE":"45A","2707 HARDING AVENUE":"45A","2461 ROHR PLACE":"45A","701 CALHOUN AVENUE":"45A","2843 LAWTON AVENUE":"45A","2879 PHILIP AVENUE":"45A","1009 BRINSMADE AVENUE":"45A","6 ALDEN PARK":"45A","1103 ELLSWORTH AVENUE":"45A","756 SWINTON AVENUE":"45A","3003 RANDALL AVENUE":"45A","871 SWINTON AVENUE":"45A","537 LOGAN AVENUE":"45A","950 CLARENCE AVENUE":"45A","3153 GRISWOLD AVENUE":"45B","827 WILCOX AVENUE":"45A","833 WILCOX AVENUE":"45A","2950 RANDALL AVENUE":"45A","3125 WISSMAN AVENUE":"45A","728 CALHOUN AVENUE":"45A","3174 HATTING PLACE":"45A","1625 RESEARCH AVENUE":"45B","920 DEAN AVENUE":"45A","846 SWINTON AVENUE":"45A","3305 COUNTRY CLUB ROAD":"45B","264 HOSMER AVENUE":"45A","2835 LAWTON AVENUE":"45A","2705 HARDING AVENUE":"45A"},"10016":{"303 5 AVENUE":"14A","QUEENS MIDTOWN TUNNEL":"17A"},"10473":{"2219 TURNBULL AVENUE":"43B","742 TAYLOR AVENUE":"43A","820 THIERIOT AVENUE":"43A","701 THIERIOT AVENUE":"43A","1894 LAFAYETTE AVENUE":"43A","SEWARD AVENUE":-1,"HAVEMEYER AVENUE":-1,"868 OLMSTEAD AVENUE":"43B","303 UNDERHILL AVENUE":"43A","GILDERSLEEVE AVENUE":-1,"BARRETT AVENUE":-1,"1842 LACOMBE AVENUE":"43A","1863 O'BRIEN AVENUE":"43A","BANES COURT":-1,"OLMSTEAD AVENUE":-1,"380 THIERIOT AVENUE":"43A","580 PUGSLEY AVENUE":"43B","CICERO AVENUE":-1,"2341 STORY AVENUE":"43B","1751 SEWARD AVENUE":"43A","917 OLMSTEAD AVENUE":"43B","347 TAYLOR AVENUE":"43A","1966 LACOMBE AVENUE":"43B","178 SOUNDVIEW AVENUE":"43A","542 BEACH AVENUE":"43A","728 TAYLOR AVENUE":"43A","437 BOLTON AVENUE":"43A","1831 PATTERSON AVENUE":"43A"},"11412":{"183-02 LIBERTY AVENUE":"103D","111-21 203 STREET":"113D","194-48 113 ROAD":"113D","109-05 191 STREET":"113D","119 AVENUE":-1,"200-19 120 AVENUE":"113D","119-16 196 STREET":"113D","104-44 205 STREET":"103D","193-22 109 AVENUE":"113D","109-14 196 STREET":"113D","191-15 116 AVENUE":"113D","118-81 RIVERTON STREET":"113B","108-40 DUNKIRK STREET":"103D","201-37 119 AVENUE":"113D","191-54 115 ROAD":"113D","195-14 HOLLIS AVENUE":"103D"},"11213":{"1617 PACIFIC STREET":"77C","1173 BERGEN STREET":"77C","4 ALICE COURT":"79A","742 MONTGOMERY STREET":"71B","740 MONTGOMERY STREET":"71B","920 EASTERN PARKWAY":"71B","MONTGOMERY STREET":-1,"728 MONTGOMERY STREET":"71B","6 ALICE COURT":"79A","1004 MONTGOMERY STREET":"71B","1224 STERLING PLACE":"77C","1785 PACIFIC STREET":"77D","1688 BERGEN STREET":"77D"},"10310":{"102 DELAFIELD PLACE":"120A","DEGROOT PLACE":-1,"20 LLEWELLYN PLACE":"120A","312 OAKLAND AVENUE":"120A","ELIZABETH AVENUE":-1,"291 OAKLAND AVENUE":"120A","36 ARCADIA PLACE":"120A","133 RAVENHURST AVENUE":"120C","45 ALPINE COURT":"120C","340 TAYLOR STREET":"120A"},"11218":{"100 STRATFORD ROAD":"70D","773 EAST    2 STREET":"70B","1346 39 STREET":"66B","397 CONEY ISLAND AVENUE":"70D","15 ARGYLE ROAD":"70D","3355 12 AVENUE":"66D","594 EAST    2 STREET":"66D","306 DITMAS AVENUE":"66D","838 MCDONALD AVENUE":"66B","210 PROSPECT PARK SOUTHWEST":"72A","545 OCEAN PARKWAY":"66D","570 OCEAN PARKWAY":"66D","540 OCEAN PARKWAY":"66D","602 OCEAN PARKWAY":"70B","170 MINNA STREET":"66D","514 OCEAN PARKWAY":"66D","535 OCEAN PARKWAY":"66D","572 OCEAN PARKWAY":"66D","228 EAST FIFTH STREET":"66D","483 OCEAN PARKWAY":"66D","470 OCEAN PARKWAY":"66D","510 OCEAN PARKWAY":"66D"},"10030":{"2 BRADHURST AVENUE":"32B","136 WEST  133 STREET":"32C","220 WEST  136 STREET":"32B","132 WEST  133 STREET":"32C","100 WEST  143 STREET":"32D","130 WEST  133 STREET":"32C","250 WEST  139 STREET":"32B","ADAM CLAYTON POWELL BOULEVARD":-1,"140 WEST  133 STREET":"32C","101 WEST  141 STREET":"32C","213 WEST  135 STREET":"32B","138 WEST  133 STREET":"32C","142 WEST  133 STREET":"32C"},"11694":{"334 BEACH  102 STREET":"100B","320 BEACH   98 STREET":"100B"},"10011":{"321 WEST   24 STREET":"10B","332 WEST   17 STREET":"10A","37 WEST   20 STREET":"13C","258 WEST   22 STREET":"10B","255 WEST   22 STREET":"10B"},"10038":{"59 MAIDEN LANE":"1A"},"10459":{"961 REV JAMES A POLITE AVENUE":"41C","EAST  168 STREET":-1,"820 EAST  168 STREET":"42D","1154 INTERVALE AVENUE":"41C","930 FOX STREET":"41D","1123 SOUTHERN BOULEVARD":"42B"},"11370":{"25-54 77 STREET":"115B","22-15 79 STREET":"114B","24-24 79 STREET":"115B","31-03 81 STREET":"115B","31-31 81 STREET":"115B","83-10 ASTORIA BOULEVARD":"115B","32-54 82 STREET":"115B","19-59 76 STREET":"114B","79 STREET":-1,"31-01 77 STREET":"115B"},"11355":{"52-06 BOWNE STREET":"109A","46-16 156 STREET":"109B","149-15 DELAWARE AVENUE":"109B","141-06 56 AVENUE":"109A","142-43 BOOTH MEMORIAL AVENUE":"109A","142-32 BOOTH MEMORIAL AVENUE":"109A","142-20 56 ROAD":"109A","148-22 59 AVENUE":"109A","56 AVENUE":-1,"56 ROAD":-1,"142-08 56 ROAD":"109A","57-11 MAIN STREET":"109A","56-16 142 STREET":"109A","137-39 45 AVENUE":"109A","134-48 60 AVENUE":"109A"},"11212":{"72 NEWPORT STREET":"73D","588 CHESTER STREET":"73D","228 EAST   91 STREET":"67C","251 EAST   91 STREET":"67C","219 EAST   91 STREET":"67C","525 THATFORD AVENUE":"73D","521 EAST   98 STREET":"73D","299 EAST   94 STREET":"67C","252 EAST   91 STREET":"67C","290 EAST   93 STREET":"67C","214 LEGION STREET":"73D"},"10456":{"1186 CLAY AVENUE":"44C","1313C CLAY AVENUE":"44E","986 FINDLAY AVENUE":"44C","905 EAGLE AVENUE":"42D","1341 CLAY AVENUE":"44E","1312 CLAY AVENUE":"44E","1200 COLLEGE AVENUE":"44C","EAST  166 STREET":-1,"1240 CLAY AVENUE":"44C","1252 CLAY AVENUE":"44C","1248 CLAY AVENUE":"44C","1258 CLAY AVENUE":"44C","1264 CLAY AVENUE":"44C","1259 CLAY AVENUE":"44C","1263 CLAY AVENUE":"44C","185 EAST  166 STREET":"44C","1122 FRANKLIN AVENUE":"42C","863 TINTON AVENUE":"40D","1088 WASHINGTON AVENUE":"42C","1405 COLLEGE AVENUE":"44E","1042 COLLEGE AVENUE":"44C","1039 COLLEGE AVENUE":"44C"},"11692":{"553 BEACH   69 STREET":"100A","122 BEACH   60 STREET":"100A","204 BEACH BREEZE LANE":"100A","203 BEACH   77 STREET":"100A","72-12 BURCHELL AVENUE":"100A","BEACH   63 STREET":-1},"11237":{"1467 GREENE AVENUE":"83D","239 MENAHAN STREET":"83D","311 JEFFERSON STREET":"83D","391 STANHOPE STREET":"83D","875 HART STREET":"83D","847 HART STREET":"83D","243 TROUTMAN STREET":"83D","388 STANHOPE STREET":"83D","300 IRVING AVENUE":"83B"},"10451":{"251 CANAL PLACE":"40B","335 EAST  151 STREET":"40C","320 EAST  156 STREET":"40C","453 EAST  160 STREET":"42C","462 EAST  160 STREET":"42C","454 EAST  160 STREET":"42C","165 EAST  156 STREET":"44A","2980 PARK AVENUE":"40C","760 GRAND CONCOURSE":"44A","333 EAST  151 STREET":"40C","495 WALTON AVENUE":"40B"},"11219":{"14 AVENUE":"66D","6315 14 AVENUE":"62A","1417 63 STREET":"62A","1453 64 STREET":"62A","1063 64 STREET":"68B","6410 NEW UTRECHT AVENUE":"62A","61 STREET":"88D","902 44 STREET":"66C","6501 NEW UTRECHT AVENUE":"62A","902 41 STREET":"66C","1367 66 STREET":"68B","5311 13 AVENUE":"66B","1566 43 STREET":"66B","1477 BAY RIDGE AVENUE":"62A","6318 15 AVENUE":"62A"},"11429":{"221-34 MURDOCK AVENUE":"105C","103-10 217 LANE":"105D","104-19 212 STREET":"105D","215-11 106 AVENUE":"105D","212-25 102 AVENUE":"105D","214-14 104 AVENUE":"105D","104-31 212 STREET":"105D","214-02 113 AVENUE":"105D","112-18 SPRINGFIELD BOULEVARD":"105D","219-29 113 DRIVE":"105C","223 STREET":-1,"102-23 215 STREET":"105D"},"11414":{"99-57 164 AVENUE":"106A","99-57 MCKEE COURT":"106A","155-17 78 STREET":"106A","163-11 CROSS BAY BOULEVARD":"106A","155-15 78 STREET":"106A","151 AVENUE":-1,"93-02 156 AVENUE":"106A","155-09 78 STREET":"106A","80-01 149 AVENUE":"106A","78-10 151 AVENUE":"106A","137-43 80 STREET":"106A","137-50 80 STREET":"106A","163-52 97 STREET":"106A","156-15 99 STREET":"106A","156-11 99 STREET":"106A","159-31 80 STREET":"106A"},"10032":{"535 WEST  163 STREET":"33A","530 WEST  163 STREET":"33A","549 WEST  163 STREET":"33A","540 WEST  163 STREET":"33A","WEST  163 STREET":-1,"286 FT WASHINGTON AVENUE":"33D","920 RIVERSIDE DRIVE":"33B","250 FT WASHINGTON AVENUE":"33D","516 WEST  169 STREET":"33C","650 WEST  168 STREET":"33B","286 FORT WASHINGTON AVENUE":"33D","671 WEST  162 STREET":"33B","300 FORT WASHINGTON AVENUE":"33D","469 WEST  166 STREET":"33A","506 WEST  166 STREET":"33A","509 WEST  166 STREET":"33A","2185 AMSTERDAM AVENUE":"33C","250 FORT WASHINGTON AVENUE":"33D","260 FORT WASHINGTON AVENUE":"33D","961 ST NICHOLAS AVENUE":"33A","954 ST NICHOLAS AVENUE":"33A","458 WEST  158 STREET":"33A","128 FORT WASHINGTON AVENUE":"33B","87 ST NICHOLAS PLACE":"30C","720 WEST  172 STREET":"33D"},"11228":{"1372 76 STREET":"68B","6924 8 AVENUE":"68D","1280 85 STREET":"68B","8424 12 AVENUE":"68B","1202 81 STREET":"68B","66 BAY   11 STREET":"62C","179 DAHLGREN PLACE":"68A","7018 8 AVENUE":"68D"},"11208":{"134 GLEN STREET":"75A","973 DUMONT AVENUE":"75B","2797 LINDEN BOULEVARD":"75C","1 AUTUMN AVENUE":"75A","183 EUCLID AVENUE":"75A","412 PINE STREET":"75C","480 CLEVELAND STREET":"75B","700 ESSEX STREET":"75D","301 NICHOLS AVENUE":"75A","54 ELDERT LANE":"75A","736 LINCOLN AVENUE":"75C","55 GRANT AVENUE":"75A","58 GRANT AVENUE":"75A","322 NICHOLS AVENUE":"75A","956 HEMLOCK STREET":"75C","1011 HEMLOCK STREET":"75C","310 ARLINGTON AVENUE":"75A","23 NICHOLS AVENUE":"75A","14 NICHOLS AVENUE":"75A","17 NICHOLS AVENUE":"75A","106 ETNA STREET":"75A","110 ETNA STREET":"75A","130 GLEN STREET":"75A","121 MCKINLEY AVENUE":"75A","388 SHEPHERD AVENUE":"75C","113 NICHOLS AVENUE":"75A","168 CLEVELAND STREET":"75A","162 CLEVELAND STREET":"75A","135 GLEN STREET":"75A","527 ELDERT LANE":"75A","529 ELDERT LANE":"75A","137 AUTUMN AVENUE":"75A","696 JAMAICA AVENUE":"75A","295 ARLINGTON AVENUE":"75A","135 AUTUMN AVENUE":"75A","51 DANFORTH STREET":"75A","535 ELDERT LANE":"75A","436 SAPPHIRE STREET":"75C","956 CRESCENT STREET":"75C","3028 FULTON STREET":"75A"},"10475":{"2049 ASCH LOOP":"45C","ASCH LOOP":-1,"ALCOTT PLACE":-1,"EARHART LANE":-1,"2240 HOLLERS AVENUE":"47C","HOLLERS AVENUE":-1,"140 ASCH LOOP":"45C","14 EARHART LANE":"45C"},"10458":{"414 EAST  187 STREET":"48B","134 EAST MOSHOLU PARKWAY SOUTH":"52C","2968 DECATUR AVENUE":"52C","364 EAST  201 STREET":"52C","314 EAST  196 STREET":"52B","2470 HOFFMAN STREET":"48A","2549 DECATUR AVENUE":"52B","606 EAST  187 STREET":"48B","2480 HOFFMAN STREET":"48A","2454 TIEBOUT AVENUE":"46B","EAST MOSHOLU PARKWAY NORTH":-1,"2780 GRAND CONCOURSE":"52B","2952 MARION AVENUE":"52C"},"11358":{"42-30 195 STREET":"111D","40-09 194 STREET":"111D","36-03 169 STREET":"109D","36-24 169 STREET":"109D","36-35 165 STREET":"109D","45-46 170 STREET":"109B","45-62 170 STREET":"109B","40-21 194 STREET":"111D","45-52 170 STREET":"109B","165 STREET":-1,"46-32 192 STREET":"111C","191-15 NORTHERN BOULEVARD":"111D","199-11 35 AVENUE":"111D","164-11 CROCHERON AVENUE":"109D","164 STREET":-1,"32-19 166 STREET":"109D","190 STREET":-1,"189-01 CROCHERON AVENUE":"111D","42-40 158 STREET":"109B","45-86 163 STREET":"109B","192-04 CROCHERON AVENUE":"111D","43-77 163 STREET":"109B"},"11367":{"64-27 138 STREET":"109A","150-66 77 AVENUE":"107D","135-26 HORACE HARDING EXPRESSWAY":"109A","136-30 HORACE HARDING EXPRESSWAY":"109A","61-51 146 STREET":"107D","141-27 79 AVENUE":"107D","141-02 79 AVENUE":"107D","141-15 78 ROAD":"107D"},"10002":{"53 STANTON STREET":"5B","MANHATTAN BRIDGE":"5A","130 SUFFOLK STREET":"7C","132 SUFFOLK STREET":"7C","91 BOWERY":"5B","81 CANAL STREET":"5B","159 EAST BROADWAY":"7A","297 DELANCEY STREET":"7B","1 BIALYSTOKER PLACE":"7B"},"11206":{"659 FLUSHING AVENUE":"90B","210 BOGART STREET":"90D","BUSHWICK AVENUE":-1,"525 MARCY AVENUE":"79D","HART STREET":-1,"535 MARCY AVENUE":"79D","11 STAGG STREET":"90C","217 HART STREET":"79C","179 MOORE STREET":"90D","392 LORIMER STREET":"90C","365 PULASKI STREET":"81A","519 MARCY AVENUE":"79D"},"11373":{"78-08 51 AVENUE":"110A","40-44 GLEANE STREET":"110A","85-19 GRAND AVENUE":"110A","40-23 ITHACA STREET":"110A","87-25 58 AVENUE":"110A","51 AVENUE":-1,"50-22 IRELAND STREET":"110A","52-100 79 STREET":"110A","40-15 WARREN STREET":"110B","40-48 ASKE STREET":"110B","95-11 41 AVENUE":"110B","41-19 WARREN STREET":"110B","44-11 KETCHAM STREET":"110B","53-50 80 STREET":"110A","84-08 52 AVENUE":"110A"},"10301":{"56 OXFORD PLACE":"120B","155 BAY STREET":"120B","FORT PLACE":-1,"59 OXFORD PLACE":"120B","45 AVON PLACE":"120B","31 HAVENWOOD ROAD":"120A","210 DANIEL LOW TERRACE":"120B","137 YORK AVENUE":"120B","133 CASTLETON AVENUE":"120B","60 OXFORD PLACE":"120B"},"11426":{"84-46 COMMONWEALTH BOULEVARD":"105E","237-19 JAMAICA AVENUE":"105E","80-01 252 STREET":"105E","253-27 86 AVENUE":"105E","237-17 JAMAICA AVENUE":"105E","93-17 239 STREET":"105E"},"11220":{"857 48 STREET":"66C","339 46 STREET":"72C","436 56 STREET":"72D","4720 3 AVENUE":"72B","9 AVENUE":"66D","5305 6 AVENUE":"72C","480 62 STREET":"72D","4 AVENUE":"66D","539 48 STREET":"72C","6735 RIDGE BOULEVARD":"68D"},"11436":{"146-01 120 AVENUE":"113A","144-02 130 AVENUE":"113A","142-44 SUTTER AVENUE":"113A","130-12 146 STREET":"113A","116-49 143 STREET":"113A","128-40 150 STREET":"113A","142-21 FOCH BOULEVARD":"113A","143-42 FOCH BOULEVARD":"113A","116-51 141 STREET":"113A","130 AVENUE":-1,"142-20 FOCH BOULEVARD":"113A","114-27 139 STREET":"113A","140-40 BASCOM AVENUE":"113A","127-14 142 STREET":"113A","142-18 FOCH BOULEVARD":"113A","142-23 FOCH BOULEVARD":"113A","145-45 NORTH CONDUIT AVENUE":"113A","138-17 115 AVENUE":"113A"},"10457":{"1857 ANTHONY AVENUE":"46A","405 EAST  182 STREET":"48B","MONROE AVENUE":-1,"1855 MONROE AVENUE":"46A","1848 MONROE AVENUE":"46A","2229 ADAMS PLACE":"48B","451 EAST TREMONT AVENUE":"48C","2041 LAFONTAINE AVENUE":"48C","CROTONA AVENUE":-1,"701 EAST  175 STREET":"48C","2130 CROTONA AVENUE":"48B","451 EAST  179 STREET":"48C","215 MOUNT HOPE PLACE":"46A","446 EAST  179 STREET":"48C","2105 RYER AVENUE":"46B","516 EAST TREMONT AVENUE":"48C","2276 ARTHUR AVENUE":"48B","2215 ADAMS PLACE":"48B","1817 TOPPING AVENUE":"46A","755 OAKLAND PLACE":"48C","2056 HUGHES AVENUE":"48C","4469 PARK AVENUE":"48B","3841 3 AVENUE":"42A","708 EAST TREMONT AVENUE":"48C","1854 MONROE AVENUE":"46A","1544 WASHINGTON AVENUE":"42A","1780 EASTBURN AVENUE":"46A","209 MOUNT HOPE PLACE":"46A"},"10312":{"168B FIGUREA AVENUE":"123C","96 RIDGEWOOD AVENUE":"122A","104 STROUD AVENUE":"123C","116 HALPIN AVENUE":"123C","2 MARNE AVENUE":"123C","44 COVINGTON CIRCLE":"123A","204 ROBINSON AVENUE":"122A"},"11040":{"270-07 82 AVENUE":"105E"},"10305":{"554 NAUGHTON AVENUE":"122B","424 ATLANTIC AVENUE":"122B","129 KRAMER STREET":"122C","375 TOMPKINS AVENUE":"120D","235 SEAVIEW AVENUE":"122B","63 BELAIR ROAD":"120D","25 RAILROAD AVENUE":"122C","131 LYNHURST AVENUE":"120D","62 BELAIR ROAD":"120D","23 CLIFTON AVENUE":"120D","50 BELAIR ROAD":"120D","50 APPLEBY AVENUE":"122C","14 COURTNEY LOOP":"120D","28 SCARBORO AVENUE":"120D","159 HYLAN BOULEVARD":"120D","153 OLYMPIA BOULEVARD":"122C","363 CROMWELL AVENUE":"122B","65 SCHOOL ROAD":"120D","40 SYLVATON TERRACE":"120D","35 SCHOOL ROAD":"120D"},"10029":{"1809 LEXINGTON AVENUE":"23D","EAST   97 STREET":-1,"2080 1 AVENUE":"23A","330 EAST  104 STREET":"23A","413 EAST  114 STREET":"23D","215 EAST   99 STREET":"23B","401 EAST  102 STREET":"23A","260 PLEASANT AVENUE":"25A","226 EAST  106 STREET":"23B","301 EAST   99 STREET":"23A","1465 PARK AVENUE":"23B","1833 LEXINGTON AVENUE":"23D","333 EAST  100 STREET":"23A"},"11372":{"35-25 92 STREET":"115D","37 AVENUE":-1,"86-02 NORTHERN BOULEVARD":"115C","34-00 85 STREET":"115C","33-29 85 STREET":"115C","85-15 35 AVENUE":"115C","33-32 84 STREET":"115C","35-41 92 STREET":"115D","88-01 37 AVENUE":"115D","35-01 80 STREET":"115C","35-42 88 STREET":"115D","93-11 34 AVENUE":"115D","34-18 76 STREET":"115C","33-21 82 STREET":"115C"},"10472":{"ELDER AVENUE":-1,"1145 NOBLE AVENUE":"43D","1041 BOYNTON AVENUE":"43C","2126 CROSS BRONX EXPRESSWAY":"43B","1190 COMMONWEALTH AVENUE":"43D","1145 CROES AVENUE":"43D","1112 COLGATE AVENUE":"43C","1226 NOBLE AVENUE":"43D","1142 ELDER AVENUE":"43C","1150 ELDER AVENUE":"43C","1140 COLGATE AVENUE":"43C","1352 ELDER AVENUE":"43C","1224 NOBLE AVENUE":"43D","1123 CROES AVENUE":"43D","1131 CROES AVENUE":"43D","1015 BOYNTON AVENUE":"43C","1144 ELDER AVENUE":"43C","1206 ELDER AVENUE":"43C","1342 THIERIOT AVENUE":"43D","2047 CHATTERTON AVENUE":"43B"},"11101":{"13 STREET":-1,"47 ROAD":-1,"37 AVENUE":-1,"DUTCH KILLS":"108B","11-21 47 ROAD":"108A","8-12 43 ROAD":"108A","13-01 JACKSON AVENUE":"108A","37-28 34 STREET":"114C","21-36 44 DRIVE":"108A","37-14 32 STREET":"114C","PLACELLA PARK":"114D","37-22 34 STREET":"114C","44-78 21 STREET":"108A","44-78 23 STREET":"108A","45-16 23 STREET":"108A","38-10 47 AVENUE":"108B"},"10474":{"638 BARRETTO STREET":"41B","850 BRYANT AVENUE":"41A","863 HUNTS POINT AVENUE":"41B","904 BRYANT AVENUE":"41A","906 BRYANT AVENUE":"41A","642 FAILE STREET":"41B"},"11221":{"LEXINGTON AVENUE":-1,"57 BLEECKER STREET":"83B","1292 JEFFERSON AVENUE":"83A","EVERGREEN AVENUE":-1,"525 LEXINGTON AVENUE":"79C"},"10025":{"37 WEST  100 STREET":"24C","210 WEST   94 STREET":"24B","133 WEST  104 STREET":"24C","BROADWAY":-1,"640 WEST  112 STREET":"26A","14 WEST  102 STREET":"24C","58 MANHATTAN AVENUE":"24C","3 WEST  101 STREET":"24C","609 WEST  114 STREET":"26A","43 WEST   93 STREET":"24B","175 WEST   95 STREET":"24B","135 WEST  102 STREET":"24C","51 WEST  104 STREET":"24C","118 WEST   95 STREET":"24B","202 WEST   96 STREET":"24B","234 RIVERSIDE DRIVE":"24A","41 WEST   94 STREET":"24B","WEST  101 STREET":-1,"37 WEST   94 STREET":"24B","70 DUKE ELLINGTON BOULEVARD":"24C","255 WEST   95 STREET":"24A","17 WEST  103 STREET":"24C","765 AMSTERDAM AVENUE":"24B","65 WEST   96 STREET":"24B","747 AMSTERDAM AVENUE":"24B","26 WEST   97 STREET":"24B","310 WEST  101 STREET":"24A","350 CENTRAL PARK WEST":"24B"},"10065":{"200 EAST   66 STREET":"19A","44 EAST   65 STREET":"19A","215 EAST   65 STREET":"19A","141 EAST   61 STREET":"19A"},"11004":{"74-62 260 STREET":"105E","74-68 260 STREET":"105E"},"10019":{"619 WEST   54 STREET":"18D","338 WEST   53 STREET":"18C","725 10 AVENUE":"18D","829 11 AVENUE":"18E","405 WEST   51 STREET":"18D","421 WEST   54 STREET":"18D","464 WEST   51 STREET":"18D","230 CENTRAL PARK SOUTH":"18E","5 AVENUE":"9A"},"10037":{"515 LENOX AVENUE":"32C"},"11360":{"16-02 BELL BOULEVARD":"109D","16-36 BELL BOULEVARD":"109D"},"11104":{"43 STREET":-1,"41 STREET":-1,"45-15 40 STREET":"108B","39-37 49 STREET":"108C","41-17 48 STREET":"108C","38-19 50 STREET":"108C","47-07 39 STREET":"108B","51-01 39 AVENUE":"108C"},"10470":{"4310 VAN CORTLANDT PARK EAST":"47B","345 EAST  236 STREET":"47B","4511 MATILDA AVENUE":"47B","348 EAST  236 STREET":"47B","633 NEREID AVENUE":"47B"},"10036":{"547 WEST   47 STREET":"18D","424 WEST   47 STREET":"18D","526 WEST   47 STREET":"18D","521 WEST   47 STREET":"18D","519 WEST   47 STREET":"18D","431 WEST   44 STREET":"18D","7 TIMES SQUARE":"14E","60 WEST   48 STREET":"18B"},"11211":{"160 SOUTH    3 STREET":"90A","754 METROPOLITAN AVENUE":"90C","216 DIVISION AVENUE":"90B","752 METROPOLITAN AVENUE":"90C","269 WITHERS STREET":"94B","333 UNION AVENUE":"90A","282 SOUTH    9 STREET":"90B","330 SOUTH    3 STREET":"90A","256 SOUTH    4 STREET":"90A","553 METROPOLITAN AVENUE":"94B","602 LORIMER STREET":"94B","97 SKILLMAN AVENUE":"94B","561 METROPOLITAN AVENUE":"94B","405 GRAND STREET":"90A","2 CONSELYEA STREET":"94B","322 RODNEY STREET":"90A","426 RODNEY STREET":"90A","339 RODNEY STREET":"90A","600 UNION AVENUE":"94A","400 RODNEY STREET":"90A","22 JUDGE STREET":"90D","296 POWERS STREET":"90D"},"10027":{"177 WEST  122 STREET":"28D","176 WEST  122 STREET":"28D","3089 BROADWAY":"26B","109 WEST  132 STREET":"32C","38 ST NICHOLAS TERRACE":"26C","102 WEST  132 STREET":"32A","213 WEST  122 STREET":"28C"},"10303":{"1585 GOETHALS ROAD NORTH":"121A","FOREST AVENUE":-1,"229 UNION AVENUE":"121A"},"10026":{"45 WEST  118 STREET":"28A","1330 5 AVENUE":"28A","257 WEST  117 STREET":"28B","137 WEST  116 STREET":"28A","139 WEST  116 STREET":"28A","309 MANHATTAN AVENUE":"26A","129 WEST  116 STREET":"28A","141 WEST  116 STREET":"28A"},"11224":{"3030 WEST   32 STREET":"60D","2851 WEST   20 STREET":"60D","2848 WEST   19 STREET":"60D","3522 SURF AVENUE":"60D","3604 SURF AVENUE":"60D","SURF AVENUE":-1,"3514 SURF AVENUE":"60D"},"11363":{"43-05 DOUGLASTON PARKWAY":"111B","43-60 DOUGLASTON PARKWAY":"111B","44-20 DOUGLASTON PARKWAY":"111B"},"10128":{"THIRD AVENUE":-1,"3 AVENUE":"9A","1553 3 AVENUE":"19D","307 EAST   90 STREET":"19D","231 EAST   88 STREET":"19D","205 EAST   88 STREET":"19D"},"10464":{"85 SCHOFIELD STREET":"45C"},"11693":{"192 BEACH   96 STREET":"100B"},"10005":{"18 PINE STREET":"1A","140 BROADWAY":"1A"},"10306":{"135 HAVEN AVENUE":"122B","27 BEACON PLACE":"122A","182 LINCOLN AVENUE":"122B","80 KELVIN AVENUE":"122A"},"10023":{"2080 BROADWAY":"20B","35 WEST   75 STREET":"20B","111 WEST   67 STREET":"20A","1968 BROADWAY":"20A","102 WEST   74 STREET":"20B","WEST   60 STREET":-1,"15 WEST   63 STREET":"20A"},"10018":{"452 5 AVENUE":"14D","542 WEST   36 STREET":"10C","360 WEST   36 STREET":"14D"},"11239":{"1520 HORNELL LOOP":"75E","EGAN STREET":-1,"768 EGAN STREET":"75E","1490 HORNELL LOOP":"75E"},"11229":{"1632 EAST   13 STREET":"61A","2221 BATCHELDER STREET":"61C","EAST   18 STREET":-1,"2311 EAST   18 STREET":"61B","1739 EAST   29 STREET":"61A","EAST   29 STREET":-1,"1710 AVENUE W":"61B","110 ASTER COURT":"61C","2020 AVENUE V":"61B"},"10007":{"305 BROADWAY":"1C","51 MURRAY STREET":"1C"},"11362":{"54-05 DOUGLASTON PARKWAY":"111B","47-14 LITTLE NECK PARKWAY":"111B","252-20 NORTHERN BOULEVARD":"111B","242-24 NORTHERN BOULEVARD":"111B"},"10010":{"396 1 AVENUE":"13D","420 EAST   23 STREET":"13D","510 EAST   23 STREET":"13D"},"10153":{"767 5 AVENUE":"18A"},"10024":{"168 WEST   83 STREET":"20C","148 WEST   83 STREET":"20C","74 WEST   91 STREET":"24B","60 WEST   91 STREET":"24B","444 COLUMBUS AVENUE":"20C","158 WEST   83 STREET":"20C"},"10028":{"230 EAST   81 STREET":"19C","228 EAST   81 STREET":"19C","1094 MADISON AVENUE":"19C","400 EAST   85 STREET":"19C"},"11249":{"22 NORTH    5 STREET":"94A","629 KENT AVENUE":"90B","420 KENT AVENUE":"90A","79 NORTH   12 STREET":"94A","450 KENT AVENUE":"90A","110 SOUTH    2 STREET":"90A","305 BERRY STREET":"90A","333 BERRY STREET":"90A","288 BERRY STREET":"90A","53 NORTH    3 STREET":"94A"},"10013":{"388 GREENWICH STREET":"1C","122 HUDSON STREET":"1C","100 LAFAYETTE STREET":"5C","131 AVENUE OF THE AMERICAS":"1D"},"10017":{"1 EAST   49 STREET":"18A"},"10014":{"227 AVENUE OF THE AMERICAS":"1D","90 MORTON STREET":"6D"},"10006":{"40 GREENWICH STREET":"1B","55 BROADWAY":"1B"},"10001":{"252 WEST   29 STREET":"10B","35 WEST   33 STREET":"14B","1220 BROADWAY":"14B","502 WEST   30 STREET":"10C","229 9 AVENUE":"10B","407 8 AVENUE":"14C","357 WEST   35 STREET":"14D","351 WEST   35 STREET":"14D"},"11411":{"117-28 223 STREET":"105C","116-15 218 STREET":"105C","114 ROAD":-1},"10308":{"235 LEVERETT AVENUE":"122A","490 ELVERTON AVENUE":"122A","497 DOANE AVENUE":"122A","245 GURLEY AVENUE":"122A","440 DOANE AVENUE":"122A","10 PARK TERRACE":"122A","446 DOANE AVENUE":"122A","15 PERONA LANE":"122A"},"10309":{"1181 WOODROW ROAD":"123A","56 AMBASSADOR LANE":"123A","155 GERVIL STREET":"123A","15 BAYSIDE LANE":"123B"},"10282":{"201 WARREN STREET":"1C"},"11210":{"1869 FLATBUSH AVENUE":"63D","1358 EAST   35 STREET":"63B","2001 AVENUE H":"70B","850 EAST   31 STREET":"70B","913 EAST   31 STREET":"63B","1210 EAST   35 STREET":"63B"},"10075":{"1374 3 AVENUE":"19C","863 PARK AVENUE":"19C","368 EAST   77 STREET":"19B","3 AVENUE":"9A"},"10035":{"EAST  118 STREET":-1,"73 EAST  118 STREET":"25C","9 EAST  118 STREET":"25C","2327 FIRST AVENUE":"25A","2325 1 AVENUE":"25A","1 EAST  117 STREET":"25C","70 EAST  125 STREET":"25C","ROBERT F KENNEDY BRIDGE":"25A"},"11366":{"172-02 73 AVENUE":"107A","176-71 UNION TURNPIKE":"107A"},"10022":{"135 EAST   50 STREET":"17B"},"11364":{"64-68 230 STREET":"111A"},"11109":{"47-40 CENTER BOULEVARD":"108A","46-30 CENTER BOULEVARD":"108A"}}